Workbook

Sheet  Employee Master Data
A1: Employee ID | B1: Full Name | C1: Gender | D1: Age | E1: Department | F1: Branch | G1: Job Grade | H1: Employment Type | I1: Education Level | J1: Hire Date | K1: Exit Date | L1: Exit Reason | M1: Status | N1: Monthly Salary ($) | O1: Manager ID | P1: Tenure (Years) | Q1: Tenure Band | R1: Hire Year | S1: Exit Year | T1: Education Level Cleaned
A2: EMP-10001 | B2: Jeffery Smith | C2: Male | D2: 39 | E2: Executive Management | F2: Central Hub | G2: Grade 5 – Lead | H2: Contract | I2: Master's Degree | J2: 43672 | K2: 45724 | L2: Resignation | M2: Inactive | N2: 18449.3 | O2: MGR-10048 | P2: 5.6 | Q2: =IF(Table1[[#This Row],[Tenure (Years)]]<1,"< 1 Year", IF(Table1[[#This Row],[Tenure (Years)]]<2,"1–2 Years", IF(Table1[[#This Row],[Tenure (Years)]]<3,"2–3 Years", IF(Table1[[#This Row],[Tenure (Years)]]<5,"3–5 Years", IF(Table1[[#This Row],[Tenure (Years)]]<10,"5–10 Years", "> 10 Years"))))) -> 5–10 Years | R2: =YEAR(Table1[[#This Row],[Hire Date]]) -> 2019 | S2: =YEAR(Table1[[#This Row],[Exit Date]]) -> 2025 | T2: =IF(Table1[[#This Row],[Education Level]]="Master's Degree", "Master's Degree", IF(Table1[[#This Row],[Education Level]]="Bachelor's Degree", "Bachelor's Degree", "Others")) -> Master's Degree
A3: EMP-10002 | B3: Laura Powell | C3: Female | D3: 33 | E3: Sales | F3: Head Office | G3: Grade 2 – Junior | H3: Permanent | I3: Bachelor's Degree | J3: 46033 | M3: Active | N3: 5505.05 | O3: MGR-10302 | P3: 0.3 | Q3: =IF(Table1[[#This Row],[Tenure (Years)]]<1,"< 1 Year", IF(Table1[[#This Row],[Tenure (Years)]]<2,"1–2 Years", IF(Table1[[#This Row],[Tenure (Years)]]<3,"2–3 Years", IF(Table1[[#This Row],[Tenure (Years)]]<5,"3–5 Years", IF(Table1[[#This Row],[Tenure (Years)]]<10,"5–10 Years", "> 10 Years"))))) -> < 1 Year | R3: =YEAR(Table1[[#This Row],[Hire Date]]) -> 2026 | T3: =IF(Table1[[#This Row],[Education Level]]="Master's Degree", "Master's Degree", IF(Table1[[#This Row],[Education Level]]="Bachelor's Degree", "Bachelor's Degree", "Others")) -> Bachelor's Degree
A4: EMP-10003 | B4: Michelle Rodriguez | C4: Female | D4: 40 | E4: IT | F4: Head Office | G4: Grade 5 – Lead | H4: Permanent | I4: Bachelor's Degree | J4: 45960 | M4: Active | N4: 14038.99 | O4: MGR-10053 | P4: 0.5 | Q4: =IF(Table1[[#This Row],[Tenure (Years)]]<1,"< 1 Year", IF(Table1[[#This Row],[Tenure (Years)]]<2,"1–2 Years", IF(Table1[[#This Row],[Tenure (Years)]]<3,"2–3 Years", IF(Table1[[#This Row],[Tenure (Years)]]<5,"3–5 Years", IF(Table1[[#This Row],[Tenure (Years)]]<10,"5–10 Years", "> 10 Years"))))) -> < 1 Year | R4: =YEAR(Table1[[#This Row],[Hire Date]]) -> 2025 | T4: =IF(Table1[[#This Row],[Education Level]]="Master's Degree", "Master's Degree", IF(Table1[[#This Row],[Education Level]]="Bachelor's Degree", "Bachelor's Degree", "Others")) -> Bachelor's Degree
A5: EMP-10004 | B5: Curtis Friedman | C5: Male | D5: 48 | E5: Human Resources | F5: South Region | G5: Grade 3 – Mid-Level | H5: Contract | I5: Master's Degree | J5: 44184 | M5: Active | N5: 7576.94 | O5: MGR-10283 | P5: 5.4 | Q5: =IF(Table1[[#This Row],[Tenure (Years)]]<1,"< 1 Year", IF(Table1[[#This Row],[Tenure (Years)]]<2,"1–2 Years", IF(Table1[[#This Row],[Tenure (Years)]]<3,"2–3 Years", IF(Table1[[#This Row],[Tenure (Years)]]<5,"3–5 Years", IF(Table1[[#This Row],[Tenure (Years)]]<10,"5–10 Years", "> 10 Years"))))) -> 5–10 Years | R5: =YEAR(Table1[[#This Row],[Hire Date]]) -> 2020 | T5: =IF(Table1[[#This Row],[Education Level]]="Master's Degree", "Master's Degree", IF(Table1[[#This Row],[Education Level]]="Bachelor's Degree", "Bachelor's Degree", "Others")) -> Master's Degree
A6: EMP-10005 | B6: Sheena Campbell | C6: Female | D6: 32 | E6: IT | F6: East Region | G6: Grade 5 – Lead | H6: Permanent | I6: Diploma | J6: 45465 | M6: Active | N6: 17711.12 | O6: MGR-10041 | P6: 1.9 | Q6: =IF(Table1[[#This Row],[Tenure (Years)]]<1,"< 1 Year", IF(Table1[[#This Row],[Tenure (Years)]]<2,"1–2 Years", IF(Table1[[#This Row],[Tenure (Years)]]<3,"2–3 Years", IF(Table1[[#This Row],[Tenure (Years)]]<5,"3–5 Years", IF(Table1[[#This Row],[Tenure (Years)]]<10,"5–10 Years", "> 10 Years"))))) -> 1–2 Years | R6: =YEAR(Table1[[#This Row],[Hire Date]]) -> 2024 | T6: =IF(Table1[[#This Row],[Education Level]]="Master's Degree", "Master's Degree", IF(Table1[[#This Row],[Education Level]]="Bachelor's Degree", "Bachelor's Degree", "Others")) -> Others
A7: EMP-10006 | B7: John Rice | C7: Male | D7: 32 | E7: Sales | F7: East Region | G7: Grade 5 – Lead | H7: Permanent | I7: Bachelor's Degree | J7: 44595 | M7: Active | N7: 16280.76 | O7: MGR-10350 | P7: 4.3 | Q7: =IF(Table1[[#This Row],[Tenure (Years)]]<1,"< 1 Year", IF(Table1[[#This Row],[Tenure (Years)]]<2,"1–2 Years", IF(Table1[[#This Row],[Tenure (Years)]]<3,"2–3 Years", IF(Table1[[#This Row],[Tenure (Years)]]<5,"3–5 Years", IF(Table1[[#This Row],[Tenure (Years)]]<10,"5–10 Years", "> 10 Years"))))) -> 3–5 Years | R7: =YEAR(Table1[[#This Row],[Hire Date]]) -> 2022 | T7: =IF(Table1[[#This Row],[Education Level]]="Master's Degree", "Master's Degree", IF(Table1[[#This Row],[Education Level]]="Bachelor's Degree", "Bachelor's Degree", "Others")) -> Bachelor's Degree
A8: EMP-10007 | B8: James Vang | C8: Male | D8: 49 | E8: Executive Management | F8: Central Hub | G8: Grade 5 – Lead | H8: Permanent | I8: Bachelor's Degree | J8: 44103 | M8: Active | N8: 17809.87 | O8: MGR-10286 | P8: 5.6 | Q8: =IF(Table1[[#This Row],[Tenure (Years)]]<1,"< 1 Year", IF(Table1[[#This Row],[Tenure (Years)]]<2,"1–2 Years", IF(Table1[[#This Row],[Tenure (Years)]]<3,"2–3 Years", IF(Table1[[#This Row],[Tenure (Years)]]<5,"3–5 Years", IF(Table1[[#This Row],[Tenure (Years)]]<10,"5–10 Years", "> 10 Years"))))) -> 5–10 Years | R8: =YEAR(Table1[[#This Row],[Hire Date]]) -> 2020 | T8: =IF(Table1[[#This Row],[Education Level]]="Master's Degree", "Master's Degree", IF(Table1[[#This Row],[Education Level]]="Bachelor's Degree", "Bachelor's Degree", "Others")) -> Bachelor's Degree
A9: EMP-10008 | B9: Jade Elliott | C9: Female | D9: 41 | E9: Sales | F9: North Region | G9: Grade 4 – Senior | H9: Contract | I9: Master's Degree | J9: 44039 | K9: 45872 | L9: Dismissal | M9: Inactive | N9: 13292.83 | O9: MGR-10162 | P9: 5 | Q9: =IF(Table1[[#This Row],[Tenure (Years)]]<1,"< 1 Year", IF(Table1[[#This Row],[Tenure (Years)]]<2,"1–2 Years", IF(Table1[[#This Row],[Tenure (Years)]]<3,"2–3 Years", IF(Table1[[#This Row],[Tenure (Years)]]<5,"3–5 Years", IF(Table1[[#This Row],[Tenure (Years)]]<10,"5–10 Years", "> 10 Years"))))) -> 5–10 Years | R9: =YEAR(Table1[[#This Row],[Hire Date]]) -> 2020 | S9: =YEAR(Table1[[#This Row],[Exit Date]]) -> 2025 | T9: =IF(Table1[[#This Row],[Education Level]]="Master's Degree", "Master's Degree", IF(Table1[[#This Row],[Education Level]]="Bachelor's Degree", "Bachelor's Degree", "Others")) -> Master's Degree
A10: EMP-10009 | B10: Nicole White | C10: Female | D10: 30 | E10: Sales | F10: East Region | G10: Grade 4 – Senior | H10: Permanent | I10: Diploma | J10: 44980 | M10: Active | N10: 11280.34 | O10: MGR-10383 | P10: 3.2 | Q10: =IF(Table1[[#This Row],[Tenure (Years)]]<1,"< 1 Year", IF(Table1[[#This Row],[Tenure (Years)]]<2,"1–2 Years", IF(Table1[[#This Row],[Tenure (Years)]]<3,"2–3 Years", IF(Table1[[#This Row],[Tenure (Years)]]<5,"3–5 Years", IF(Table1[[#This Row],[Tenure (Years)]]<10,"5–10 Years", "> 10 Years"))))) -> 3–5 Years | R10: =YEAR(Table1[[#This Row],[Hire Date]]) -> 2023 | T10: =IF(Table1[[#This Row],[Education Level]]="Master's Degree", "Master's Degree", IF(Table1[[#This Row],[Education Level]]="Bachelor's Degree", "Bachelor's Degree", "Others")) -> Others
A11: EMP-10010 | B11: Brett Bowen | C11: Male | D11: 39 | E11: Procurement | F11: Head Office | G11: Grade 3 – Mid-Level | H11: Permanent | I11: Diploma | J11: 43667 | K11: 45934 | L11: Resignation | M11: Inactive | N11: 8250.6 | O11: MGR-10349 | P11: 6.2 | Q11: =IF(Table1[[#This Row],[Tenure (Years)]]<1,"< 1 Year", IF(Table1[[#This Row],[Tenure (Years)]]<2,"1–2 Years", IF(Table1[[#This Row],[Tenure (Years)]]<3,"2–3 Years", IF(Table1[[#This Row],[Tenure (Years)]]<5,"3–5 Years", IF(Table1[[#This Row],[Tenure (Years)]]<10,"5–10 Years", "> 10 Years"))))) -> 5–10 Years | R11: =YEAR(Table1[[#This Row],[Hire Date]]) -> 2019 | S11: =YEAR(Table1[[#This Row],[Exit Date]]) -> 2025 | T11: =IF(Table1[[#This Row],[Education Level]]="Master's Degree", "Master's Degree", IF(Table1[[#This Row],[Education Level]]="Bachelor's Degree", "Bachelor's Degree", "Others")) -> Others
A12: EMP-10011 | B12: Emily Ross | C12: Female | D12: 30 | E12: Marketing | F12: West Region | G12: Grade 4 – Senior | H12: Permanent | I12: Professional Certification | J12: 45018 | K12: 46030 | L12: Resignation | M12: Inactive | N12: 11231.45 | O12: MGR-10454 | P12: 2.8 | Q12: =IF(Table1[[#This Row],[Tenure (Years)]]<1,"< 1 Year", IF(Table1[[#This Row],[Tenure (Years)]]<2,"1–2 Years", IF(Table1[[#This Row],[Tenure (Years)]]<3,"2–3 Years", IF(Table1[[#This Row],[Tenure (Years)]]<5,"3–5 Years", IF(Table1[[#This Row],[Tenure (Years)]]<10,"5–10 Years", "> 10 Years"))))) -> 2–3 Years | R12: =YEAR(Table1[[#This Row],[Hire Date]]) -> 2023 | S12: =YEAR(Table1[[#This Row],[Exit Date]]) -> 2026 | T12: =IF(Table1[[#This Row],[Education Level]]="Master's Degree", "Master's Degree", IF(Table1[[#This Row],[Education Level]]="Bachelor's Degree", "Bachelor's Degree", "Others")) -> Others
A13: EMP-10012 | B13: Kevin Rodriguez | C13: Male | D13: 30 | E13: Customer Service | F13: Central Hub | G13: Grade 3 – Mid-Level | H13: Permanent | I13: Bachelor's Degree | J13: 44303 | M13: Active | N13: 8805.8 | O13: MGR-10135 | P13: 5.1 | Q13: =IF(Table1[[#This Row],[Tenure (Years)]]<1,"< 1 Year", IF(Table1[[#This Row],[Tenure (Years)]]<2,"1–2 Years", IF(Table1[[#This Row],[Tenure (Years)]]<3,"2–3 Years", IF(Table1[[#This Row],[Tenure (Years)]]<5,"3–5 Years", IF(Table1[[#This Row],[Tenure (Years)]]<10,"5–10 Years", "> 10 Years"))))) -> 5–10 Years | R13: =YEAR(Table1[[#This Row],[Hire Date]]) -> 2021 | T13: =IF(Table1[[#This Row],[Education Level]]="Master's Degree", "Master's Degree", IF(Table1[[#This Row],[Education Level]]="Bachelor's Degree", "Bachelor's Degree", "Others")) -> Bachelor's Degree
A14: EMP-10013 | B14: Patrick Williams | C14: Male | D14: 37 | E14: Customer Service | F14: South Region | G14: Grade 3 – Mid-Level | H14: Permanent | I14: Bachelor's Degree | J14: 45662 | M14: Active | N14: 8023.05 | O14: MGR-10391 | P14: 1.4 | Q14: =IF(Table1[[#This Row],[Tenure (Years)]]<1,"< 1 Year", IF(Table1[[#This Row],[Tenure (Years)]]<2,"1–2 Years", IF(Table1[[#This Row],[Tenure (Years)]]<3,"2–3 Years", IF(Table1[[#This Row],[Tenure (Years)]]<5,"3–5 Years", IF(Table1[[#This Row],[Tenure (Years)]]<10,"5–10 Years", "> 10 Years"))))) -> 1–2 Years | R14: =YEAR(Table1[[#This Row],[Hire Date]]) -> 2025 | T14: =IF(Table1[[#This Row],[Education Level]]="Master's Degree", "Master's Degree", IF(Table1[[#This Row],[Education Level]]="Bachelor's Degree", "Bachelor's Degree", "Others")) -> Bachelor's Degree
A15: EMP-10014 | B15: Michael Griffith | C15: Male | D15: 22 | E15: Operations | F15: Head Office | G15: Grade 3 – Mid-Level | H15: Permanent | I15: Bachelor's Degree | J15: 43103 | M15: Active | N15: 8835.88 | O15: MGR-10426 | P15: 8.4 | Q15: =IF(Table1[[#This Row],[Tenure (Years)]]<1,"< 1 Year", IF(Table1[[#This Row],[Tenure (Years)]]<2,"1–2 Years", IF(Table1[[#This Row],[Tenure (Years)]]<3,"2–3 Years", IF(Table1[[#This Row],[Tenure (Years)]]<5,"3–5 Years", IF(Table1[[#This Row],[Tenure (Years)]]<10,"5–10 Years", "> 10 Years"))))) -> 5–10 Years | R15: =YEAR(Table1[[#This Row],[Hire Date]]) -> 2018 | T15: =IF(Table1[[#This Row],[Education Level]]="Master's Degree", "Master's Degree", IF(Table1[[#This Row],[Education Level]]="Bachelor's Degree", "Bachelor's Degree", "Others")) -> Bachelor's Degree
A16: EMP-10015 | B16: Carol Thornton | C16: Female | D16: 22 | E16: IT | F16: Head Office | G16: Grade 3 – Mid-Level | H16: Permanent | I16: Bachelor's Degree | J16: 43423 | M16: Active | N16: 7222.61 | O16: MGR-10393 | P16: 7.5 | Q16: =IF(Table1[[#This Row],[Tenure (Years)]]<1,"< 1 Year", IF(Table1[[#This Row],[Tenure (Years)]]<2,"1–2 Years", IF(Table1[[#This Row],[Tenure (Years)]]<3,"2–3 Years", IF(Table1[[#This Row],[Tenure (Years)]]<5,"3–5 Years", IF(Table1[[#This Row],[Tenure (Years)]]<10,"5–10 Years", "> 10 Years"))))) -> 5–10 Years | R16: =YEAR(Table1[[#This Row],[Hire Date]]) -> 2018 | T16: =IF(Table1[[#This Row],[Education Level]]="Master's Degree", "Master's Degree", IF(Table1[[#This Row],[Education Level]]="Bachelor's Degree", "Bachelor's Degree", "Others")) -> Bachelor's Degree
A17: EMP-10016 | B17: Nicholas Alexander | C17: Male | D17: 29 | E17: Operations | F17: Central Hub | G17: Grade 1 – Entry | H17: Permanent | I17: Bachelor's Degree | J17: 44186 | M17: Active | N17: 3212.92 | O17: MGR-10387 | P17: 5.4 | Q17: =IF(Table1[[#This Row],[Tenure (Years)]]<1,"< 1 Year", IF(Table1[[#This Row],[Tenure (Years)]]<2,"1–2 Years", IF(Table1[[#This Row],[Tenure (Years)]]<3,"2–3 Years", IF(Table1[[#This Row],[Tenure (Years)]]<5,"3–5 Years", IF(Table1[[#This Row],[Tenure (Years)]]<10,"5–10 Years", "> 10 Years"))))) -> 5–10 Years | R17: =YEAR(Table1[[#This Row],[Hire Date]]) -> 2020 | T17: =IF(Table1[[#This Row],[Education Level]]="Master's Degree", "Master's Degree", IF(Table1[[#This Row],[Education Level]]="Bachelor's Degree", "Bachelor's Degree", "Others")) -> Bachelor's Degree
A18: EMP-10017 | B18: Caitlin Morgan | C18: Female | D18: 25 | E18: Sales | F18: Head Office | G18: Grade 4 – Senior | H18: Permanent | I18: Bachelor's Degree | J18: 44630 | M18: Active | N18: 11295.47 | O18: MGR-10174 | P18: 4.2 | Q18: =IF(Table1[[#This Row],[Tenure (Years)]]<1,"< 1 Year", IF(Table1[[#This Row],[Tenure (Years)]]<2,"1–2 Years", IF(Table1[[#This Row],[Tenure (Years)]]<3,"2–3 Years", IF(Table1[[#This Row],[Tenure (Years)]]<5,"3–5 Years", IF(Table1[[#This Row],[Tenure (Years)]]<10,"5–10 Years", "> 10 Years"))))) -> 3–5 Years | R18: =YEAR(Table1[[#This Row],[Hire Date]]) -> 2022 | T18: =IF(Table1[[#This Row],[Education Level]]="Master's Degree", "Master's Degree", IF(Table1[[#This Row],[Education Level]]="Bachelor's Degree", "Bachelor's Degree", "Others")) -> Bachelor's Degree
A19: EMP-10018 | B19: Jeffrey Sanchez | C19: Male | D19: 37 | E19: Finance | F19: Head Office | G19: Grade 4 – Senior | H19: Permanent | I19: Diploma | J19: 43391 | K19: 45630 | L19: Resignation | M19: Inactive | N19: 10535.52 | O19: MGR-10122 | P19: 6.1 | Q19: =IF(Table1[[#This Row],[Tenure (Years)]]<1,"< 1 Year", IF(Table1[[#This Row],[Tenure (Years)]]<2,"1–2 Years", IF(Table1[[#This Row],[Tenure (Years)]]<3,"2–3 Years", IF(Table1[[#This Row],[Tenure (Years)]]<5,"3–5 Years", IF(Table1[[#This Row],[Tenure (Years)]]<10,"5–10 Years", "> 10 Years"))))) -> 5–10 Years | R19: =YEAR(Table1[[#This Row],[Hire Date]]) -> 2018 | S19: =YEAR(Table1[[#This Row],[Exit Date]]) -> 2024 | T19: =IF(Table1[[#This Row],[Education Level]]="Master's Degree", "Master's Degree", IF(Table1[[#This Row],[Education Level]]="Bachelor's Degree", "Bachelor's Degree", "Others")) -> Others
A20: EMP-10019 | B20: Andrew Mcconnell | C20: Male | D20: 26 | E20: IT | F20: North Region | G20: Grade 4 – Senior | H20: Permanent | I20: Bachelor's Degree | J20: 45439 | M20: Active | N20: 10464.07 | O20: MGR-10049 | P20: 2 | Q20: =IF(Table1[[#This Row],[Tenure (Years)]]<1,"< 1 Year", IF(Table1[[#This Row],[Tenure (Years)]]<2,"1–2 Years", IF(Table1[[#This Row],[Tenure (Years)]]<3,"2–3 Years", IF(Table1[[#This Row],[Tenure (Years)]]<5,"3–5 Years", IF(Table1[[#This Row],[Tenure (Years)]]<10,"5–10 Years", "> 10 Years"))))) -> 2–3 Years | R20: =YEAR(Table1[[#This Row],[Hire Date]]) -> 2024 | T20: =IF(Table1[[#This Row],[Education Level]]="Master's Degree", "Master's Degree", IF(Table1[[#This Row],[Education Level]]="Bachelor's Degree", "Bachelor's Degree", "Others")) -> Bachelor's Degree
A21: EMP-10020 | B21: Terry Armstrong | C21: Male | D21: 22 | E21: Human Resources | F21: South Region | G21: Grade 4 – Senior | H21: Permanent | I21: Master's Degree | J21: 46087 | M21: Active | N21: 11094.34 | O21: MGR-10032 | P21: 0.2 | Q21: =IF(Table1[[#This Row],[Tenure (Years)]]<1,"< 1 Year", IF(Table1[[#This Row],[Tenure (Years)]]<2,"1–2 Years", IF(Table1[[#This Row],[Tenure (Years)]]<3,"2–3 Years", IF(Table1[[#This Row],[Tenure (Years)]]<5,"3–5 Years", IF(Table1[[#This Row],[Tenure (Years)]]<10,"5–10 Years", "> 10 Years"))))) -> < 1 Year | R21: =YEAR(Table1[[#This Row],[Hire Date]]) -> 2026 | T21: =IF(Table1[[#This Row],[Education Level]]="Master's Degree", "Master's Degree", IF(Table1[[#This Row],[Education Level]]="Bachelor's Degree", "Bachelor's Degree", "Others")) -> Master's Degree
A22: EMP-10021 | B22: Eric Anderson | C22: Male | D22: 48 | E22: Marketing | F22: North Region | G22: Grade 4 – Senior | H22: Permanent | I22: Bachelor's Degree | J22: 43885 | M22: Active | N22: 13102.67 | O22: MGR-10128 | P22: 6.2 | Q22: =IF(Table1[[#This Row],[Tenure (Years)]]<1,"< 1 Year", IF(Table1[[#This Row],[Tenure (Years)]]<2,"1–2 Years", IF(Table1[[#This Row],[Tenure (Years)]]<3,"2–3 Years", IF(Table1[[#This Row],[Tenure (Years)]]<5,"3–5 Years", IF(Table1[[#This Row],[Tenure (Years)]]<10,"5–10 Years", "> 10 Years"))))) -> 5–10 Years | R22: =YEAR(Table1[[#This Row],[Hire Date]]) -> 2020 | T22: =IF(Table1[[#This Row],[Education Level]]="Master's Degree", "Master's Degree", IF(Table1[[#This Row],[Education Level]]="Bachelor's Degree", "Bachelor's Degree", "Others")) -> Bachelor's Degree
A23: EMP-10022 | B23: Jenna Butler | C23: Female | D23: 32 | E23: Human Resources | F23: Head Office | G23: Grade 3 – Mid-Level | H23: Permanent | I23: Bachelor's Degree | J23: 43308 | K23: 46063 | L23: Redundancy | M23: Inactive | N23: 9084.05 | O23: MGR-10086 | P23: 7.5 | Q23: =IF(Table1[[#This Row],[Tenure (Years)]]<1,"< 1 Year", IF(Table1[[#This Row],[Tenure (Years)]]<2,"1–2 Years", IF(Table1[[#This Row],[Tenure (Years)]]<3,"2–3 Years", IF(Table1[[#This Row],[Tenure (Years)]]<5,"3–5 Years", IF(Table1[[#This Row],[Tenure (Years)]]<10,"5–10 Years", "> 10 Years"))))) -> 5–10 Years | R23: =YEAR(Table1[[#This Row],[Hire Date]]) -> 2018 | S23: =YEAR(Table1[[#This Row],[Exit Date]]) -> 2026 | T23: =IF(Table1[[#This Row],[Education Level]]="Master's Degree", "Master's Degree", IF(Table1[[#This Row],[Education Level]]="Bachelor's Degree", "Bachelor's Degree", "Others")) -> Bachelor's Degree
A24: EMP-10023 | B24: Adam Ross | C24: Male | D24: 35 | E24: Marketing | F24: North Region | G24: Grade 3 – Mid-Level | H24: Permanent | I24: High School | J24: 43341 | M24: Active | N24: 7141.24 | O24: MGR-10402 | P24: 7.7 | Q24: =IF(Table1[[#This Row],[Tenure (Years)]]<1,"< 1 Year", IF(Table1[[#This Row],[Tenure (Years)]]<2,"1–2 Years", IF(Table1[[#This Row],[Tenure (Years)]]<3,"2–3 Years", IF(Table1[[#This Row],[Tenure (Years)]]<5,"3–5 Years", IF(Table1[[#This Row],[Tenure (Years)]]<10,"5–10 Years", "> 10 Years"))))) -> 5–10 Years | R24: =YEAR(Table1[[#This Row],[Hire Date]]) -> 2018 | T24: =IF(Table1[[#This Row],[Education Level]]="Master's Degree", "Master's Degree", IF(Table1[[#This Row],[Education Level]]="Bachelor's Degree", "Bachelor's Degree", "Others")) -> Others
A25: EMP-10024 | B25: Andrea Hall | C25: Female | D25: 22 | E25: Risk & Compliance | F25: Head Office | G25: Grade 3 – Mid-Level | H25: Permanent | I25: Bachelor's Degree | J25: 45377 | M25: Active | N25: 8589.77 | O25: MGR-10030 | P25: 2.1 | Q25: =IF(Table1[[#This Row],[Tenure (Years)]]<1,"< 1 Year", IF(Table1[[#This Row],[Tenure (Years)]]<2,"1–2 Years", IF(Table1[[#This Row],[Tenure (Years)]]<3,"2–3 Years", IF(Table1[[#This Row],[Tenure (Years)]]<5,"3–5 Years", IF(Table1[[#This Row],[Tenure (Years)]]<10,"5–10 Years", "> 10 Years"))))) -> 2–3 Years | R25: =YEAR(Table1[[#This Row],[Hire Date]]) -> 2024 | T25: =IF(Table1[[#This Row],[Education Level]]="Master's Degree", "Master's Degree", IF(Table1[[#This Row],[Education Level]]="Bachelor's Degree", "Bachelor's Degree", "Others")) -> Bachelor's Degree
A26: EMP-10025 | B26: David Savage | C26: Male | D26: 30 | E26: Procurement | F26: West Region | G26: Grade 4 – Senior | H26: Permanent | I26: Bachelor's Degree | J26: 43306 | M26: Active | N26: 9774.31 | O26: MGR-10492 | P26: 7.8 | Q26: =IF(Table1[[#This Row],[Tenure (Years)]]<1,"< 1 Year", IF(Table1[[#This Row],[Tenure (Years)]]<2,"1–2 Years", IF(Table1[[#This Row],[Tenure (Years)]]<3,"2–3 Years", IF(Table1[[#This Row],[Tenure (Years)]]<5,"3–5 Years", IF(Table1[[#This Row],[Tenure (Years)]]<10,"5–10 Years", "> 10 Years"))))) -> 5–10 Years | R26: =YEAR(Table1[[#This Row],[Hire Date]]) -> 2018 | T26: =IF(Table1[[#This Row],[Education Level]]="Master's Degree", "Master's Degree", IF(Table1[[#This Row],[Education Level]]="Bachelor's Degree", "Bachelor's Degree", "Others")) -> Bachelor's Degree
A27: EMP-10026 | B27: Elizabeth Matthews | C27: Female | D27: 35 | E27: Customer Service | F27: Central Hub | G27: Grade 1 – Entry | H27: Contract | I27: Bachelor's Degree | J27: 45866 | M27: Active | N27: 2778.74 | O27: MGR-10021 | P27: 0.8 | Q27: =IF(Table1[[#This Row],[Tenure (Years)]]<1,"< 1 Year", IF(Table1[[#This Row],[Tenure (Years)]]<2,"1–2 Years", IF(Table1[[#This Row],[Tenure (Years)]]<3,"2–3 Years", IF(Table1[[#This Row],[Tenure (Years)]]<5,"3–5 Years", IF(Table1[[#This Row],[Tenure (Years)]]<10,"5–10 Years", "> 10 Years"))))) -> < 1 Year | R27: =YEAR(Table1[[#This Row],[Hire Date]]) -> 2025 | T27: =IF(Table1[[#This Row],[Education Level]]="Master's Degree", "Master's Degree", IF(Table1[[#This Row],[Education Level]]="Bachelor's Degree", "Bachelor's Degree", "Others")) -> Bachelor's Degree
A28: EMP-10027 | B28: Paula Cunningham | C28: Female | D28: 24 | E28: Procurement | F28: East Region | G28: Grade 1 – Entry | H28: Internship | I28: Bachelor's Degree | J28: 44396 | K28: 44639 | L28: End of Contract | M28: Inactive | N28: 3486.06 | O28: MGR-10235 | P28: 0.7 | Q28: =IF(Table1[[#This Row],[Tenure (Years)]]<1,"< 1 Year", IF(Table1[[#This Row],[Tenure (Years)]]<2,"1–2 Years", IF(Table1[[#This Row],[Tenure (Years)]]<3,"2–3 Years", IF(Table1[[#This Row],[Tenure (Years)]]<5,"3–5 Years", IF(Table1[[#This Row],[Tenure (Years)]]<10,"5–10 Years", "> 10 Years"))))) -> < 1 Year | R28: =YEAR(Table1[[#This Row],[Hire Date]]) -> 2021 | S28: =YEAR(Table1[[#This Row],[Exit Date]]) -> 2022 | T28: =IF(Table1[[#This Row],[Education Level]]="Master's Degree", "Master's Degree", IF(Table1[[#This Row],[Education Level]]="Bachelor's Degree", "Bachelor's Degree", "Others")) -> Bachelor's Degree
A29: EMP-10028 | B29: Robert Campbell | C29: Male | D29: 38 | E29: Legal | F29: Head Office | G29: Grade 6 – Manager | H29: Part-Time | I29: Professional Certification | J29: 45645 | M29: Active | N29: 29357.34 | O29: MGR-10136 | P29: 1.4 | Q29: =IF(Table1[[#This Row],[Tenure (Years)]]<1,"< 1 Year", IF(Table1[[#This Row],[Tenure (Years)]]<2,"1–2 Years", IF(Table1[[#This Row],[Tenure (Years)]]<3,"2–3 Years", IF(Table1[[#This Row],[Tenure (Years)]]<5,"3–5 Years", IF(Table1[[#This Row],[Tenure (Years)]]<10,"5–10 Years", "> 10 Years"))))) -> 1–2 Years | R29: =YEAR(Table1[[#This Row],[Hire Date]]) -> 2024 | T29: =IF(Table1[[#This Row],[Education Level]]="Master's Degree", "Master's Degree", IF(Table1[[#This Row],[Education Level]]="Bachelor's Degree", "Bachelor's Degree", "Others")) -> Others
A30: EMP-10029 | B30: Elizabeth Armstrong | C30: Female | D30: 29 | E30: Operations | F30: South Region | G30: Grade 5 – Lead | H30: Permanent | I30: Bachelor's Degree | J30: 44614 | M30: Active | N30: 19285.19 | O30: MGR-10414 | P30: 4.2 | Q30: =IF(Table1[[#This Row],[Tenure (Years)]]<1,"< 1 Year", IF(Table1[[#This Row],[Tenure (Years)]]<2,"1–2 Years", IF(Table1[[#This Row],[Tenure (Years)]]<3,"2–3 Years", IF(Table1[[#This Row],[Tenure (Years)]]<5,"3–5 Years", IF(Table1[[#This Row],[Tenure (Years)]]<10,"5–10 Years", "> 10 Years"))))) -> 3–5 Years | R30: =YEAR(Table1[[#This Row],[Hire Date]]) -> 2022 | T30: =IF(Table1[[#This Row],[Education Level]]="Master's Degree", "Master's Degree", IF(Table1[[#This Row],[Education Level]]="Bachelor's Degree", "Bachelor's Degree", "Others")) -> Bachelor's Degree
A31: EMP-10030 | B31: Julie Thompson | C31: Female | D31: 32 | E31: Executive Management | F31: Head Office | G31: Grade 7 – Director | H31: Permanent | I31: Master's Degree | J31: 45818 | M31: Active | N31: 40017.95 | O31: N/A | P31: 0.9 | Q31: =IF(Table1[[#This Row],[Tenure (Years)]]<1,"< 1 Year", IF(Table1[[#This Row],[Tenure (Years)]]<2,"1–2 Years", IF(Table1[[#This Row],[Tenure (Years)]]<3,"2–3 Years", IF(Table1[[#This Row],[Tenure (Years)]]<5,"3–5 Years", IF(Table1[[#This Row],[Tenure (Years)]]<10,"5–10 Years", "> 10 Years"))))) -> < 1 Year | R31: =YEAR(Table1[[#This Row],[Hire Date]]) -> 2025 | T31: =IF(Table1[[#This Row],[Education Level]]="Master's Degree", "Master's Degree", IF(Table1[[#This Row],[Education Level]]="Bachelor's Degree", "Bachelor's Degree", "Others")) -> Master's Degree
A32: EMP-10031 | B32: Stephen Hodges | C32: Male | D32: 29 | E32: Customer Service | F32: Head Office | G32: Grade 1 – Entry | H32: Permanent | I32: Bachelor's Degree | J32: 44505 | M32: Active | N32: 2922.63 | O32: MGR-10464 | P32: 4.5 | Q32: =IF(Table1[[#This Row],[Tenure (Years)]]<1,"< 1 Year", IF(Table1[[#This Row],[Tenure (Years)]]<2,"1–2 Years", IF(Table1[[#This Row],[Tenure (Years)]]<3,"2–3 Years", IF(Table1[[#This Row],[Tenure (Years)]]<5,"3–5 Years", IF(Table1[[#This Row],[Tenure (Years)]]<10,"5–10 Years", "> 10 Years"))))) -> 3–5 Years | R32: =YEAR(Table1[[#This Row],[Hire Date]]) -> 2021 | T32: =IF(Table1[[#This Row],[Education Level]]="Master's Degree", "Master's Degree", IF(Table1[[#This Row],[Education Level]]="Bachelor's Degree", "Bachelor's Degree", "Others")) -> Bachelor's Degree
A33: EMP-10032 | B33: Guy Blevins | C33: Male | D33: 51 | E33: Finance | F33: Central Hub | G33: Grade 2 – Junior | H33: Permanent | I33: Diploma | J33: 43115 | M33: Active | N33: 5058.94 | O33: MGR-10227 | P33: 8.3 | Q33: =IF(Table1[[#This Row],[Tenure (Years)]]<1,"< 1 Year", IF(Table1[[#This Row],[Tenure (Years)]]<2,"1–2 Years", IF(Table1[[#This Row],[Tenure (Years)]]<3,"2–3 Years", IF(Table1[[#This Row],[Tenure (Years)]]<5,"3–5 Years", IF(Table1[[#This Row],[Tenure (Years)]]<10,"5–10 Years", "> 10 Years"))))) -> 5–10 Years | R33: =YEAR(Table1[[#This Row],[Hire Date]]) -> 2018 | T33: =IF(Table1[[#This Row],[Education Level]]="Master's Degree", "Master's Degree", IF(Table1[[#This Row],[Education Level]]="Bachelor's Degree", "Bachelor's Degree", "Others")) -> Others
A34: EMP-10033 | B34: Kevin Miranda | C34: Male | D34: 34 | E34: Customer Service | F34: West Region | G34: Grade 3 – Mid-Level | H34: Internship | I34: Bachelor's Degree | J34: 45931 | K34: 46086 | L34: End of Contract | M34: Inactive | N34: 8182.72 | O34: MGR-10022 | P34: 0.4 | Q34: =IF(Table1[[#This Row],[Tenure (Years)]]<1,"< 1 Year", IF(Table1[[#This Row],[Tenure (Years)]]<2,"1–2 Years", IF(Table1[[#This Row],[Tenure (Years)]]<3,"2–3 Years", IF(Table1[[#This Row],[Tenure (Years)]]<5,"3–5 Years", IF(Table1[[#This Row],[Tenure (Years)]]<10,"5–10 Years", "> 10 Years"))))) -> < 1 Year | R34: =YEAR(Table1[[#This Row],[Hire Date]]) -> 2025 | S34: =YEAR(Table1[[#This Row],[Exit Date]]) -> 2026 | T34: =IF(Table1[[#This Row],[Education Level]]="Master's Degree", "Master's Degree", IF(Table1[[#This Row],[Education Level]]="Bachelor's Degree", "Bachelor's Degree", "Others")) -> Bachelor's Degree
A35: EMP-10034 | B35: Virginia Smith | C35: Female | D35: 25 | E35: IT | F35: Head Office | G35: Grade 3 – Mid-Level | H35: Contract | I35: Bachelor's Degree | J35: 43264 | K35: 46090 | L35: End of Contract | M35: Inactive | N35: 9299.26 | O35: MGR-10448 | P35: 7.7 | Q35: =IF(Table1[[#This Row],[Tenure (Years)]]<1,"< 1 Year", IF(Table1[[#This Row],[Tenure (Years)]]<2,"1–2 Years", IF(Table1[[#This Row],[Tenure (Years)]]<3,"2–3 Years", IF(Table1[[#This Row],[Tenure (Years)]]<5,"3–5 Years", IF(Table1[[#This Row],[Tenure (Years)]]<10,"5–10 Years", "> 10 Years"))))) -> 5–10 Years | R35: =YEAR(Table1[[#This Row],[Hire Date]]) -> 2018 | S35: =YEAR(Table1[[#This Row],[Exit Date]]) -> 2026 | T35: =IF(Table1[[#This Row],[Education Level]]="Master's Degree", "Master's Degree", IF(Table1[[#This Row],[Education Level]]="Bachelor's Degree", "Bachelor's Degree", "Others")) -> Bachelor's Degree
A36: EMP-10035 | B36: Katrina Nguyen | C36: Female | D36: 42 | E36: Marketing | F36: West Region | G36: Grade 7 – Director | H36: Contract | I36: Professional Certification | J36: 44070 | K36: 44590 | L36: End of Contract | M36: Inactive | N36: 41242.16 | O36: N/A | P36: 1.4 | Q36: =IF(Table1[[#This Row],[Tenure (Years)]]<1,"< 1 Year", IF(Table1[[#This Row],[Tenure (Years)]]<2,"1–2 Years", IF(Table1[[#This Row],[Tenure (Years)]]<3,"2–3 Years", IF(Table1[[#This Row],[Tenure (Years)]]<5,"3–5 Years", IF(Table1[[#This Row],[Tenure (Years)]]<10,"5–10 Years", "> 10 Years"))))) -> 1–2 Years | R36: =YEAR(Table1[[#This Row],[Hire Date]]) -> 2020 | S36: =YEAR(Table1[[#This Row],[Exit Date]]) -> 2022 | T36: =IF(Table1[[#This Row],[Education Level]]="Master's Degree", "Master's Degree", IF(Table1[[#This Row],[Education Level]]="Bachelor's Degree", "Bachelor's Degree", "Others")) -> Others
A37: EMP-10036 | B37: Mary Clarke | C37: Female | D37: 24 | E37: Marketing | F37: North Region | G37: Grade 5 – Lead | H37: Permanent | I37: Master's Degree | J37: 44193 | K37: 45773 | L37: Resignation | M37: Inactive | N37: 19184.38 | O37: MGR-10419 | P37: 4.3 | Q37: =IF(Table1[[#This Row],[Tenure (Years)]]<1,"< 1 Year", IF(Table1[[#This Row],[Tenure (Years)]]<2,"1–2 Years", IF(Table1[[#This Row],[Tenure (Years)]]<3,"2–3 Years", IF(Table1[[#This Row],[Tenure (Years)]]<5,"3–5 Years", IF(Table1[[#This Row],[Tenure (Years)]]<10,"5–10 Years", "> 10 Years"))))) -> 3–5 Years | R37: =YEAR(Table1[[#This Row],[Hire Date]]) -> 2020 | S37: =YEAR(Table1[[#This Row],[Exit Date]]) -> 2025 | T37: =IF(Table1[[#This Row],[Education Level]]="Master's Degree", "Master's Degree", IF(Table1[[#This Row],[Education Level]]="Bachelor's Degree", "Bachelor's Degree", "Others")) -> Master's Degree
A38: EMP-10037 | B38: Ashley Clark | C38: Female | D38: 36 | E38: Risk & Compliance | F38: Head Office | G38: Grade 3 – Mid-Level | H38: Permanent | I38: Bachelor's Degree | J38: 44014 | M38: Active | N38: 8961.61 | O38: MGR-10496 | P38: 5.9 | Q38: =IF(Table1[[#This Row],[Tenure (Years)]]<1,"< 1 Year", IF(Table1[[#This Row],[Tenure (Years)]]<2,"1–2 Years", IF(Table1[[#This Row],[Tenure (Years)]]<3,"2–3 Years", IF(Table1[[#This Row],[Tenure (Years)]]<5,"3–5 Years", IF(Table1[[#This Row],[Tenure (Years)]]<10,"5–10 Years", "> 10 Years"))))) -> 5–10 Years | R38: =YEAR(Table1[[#This Row],[Hire Date]]) -> 2020 | T38: =IF(Table1[[#This Row],[Education Level]]="Master's Degree", "Master's Degree", IF(Table1[[#This Row],[Education Level]]="Bachelor's Degree", "Bachelor's Degree", "Others")) -> Bachelor's Degree
A39: EMP-10038 | B39: Cynthia White | C39: Female | D39: 22 | E39: IT | F39: West Region | G39: Grade 3 – Mid-Level | H39: Permanent | I39: High School | J39: 45297 | M39: Active | N39: 8028.22 | O39: MGR-10298 | P39: 2.4 | Q39: =IF(Table1[[#This Row],[Tenure (Years)]]<1,"< 1 Year", IF(Table1[[#This Row],[Tenure (Years)]]<2,"1–2 Years", IF(Table1[[#This Row],[Tenure (Years)]]<3,"2–3 Years", IF(Table1[[#This Row],[Tenure (Years)]]<5,"3–5 Years", IF(Table1[[#This Row],[Tenure (Years)]]<10,"5–10 Years", "> 10 Years"))))) -> 2–3 Years | R39: =YEAR(Table1[[#This Row],[Hire Date]]) -> 2024 | T39: =IF(Table1[[#This Row],[Education Level]]="Master's Degree", "Master's Degree", IF(Table1[[#This Row],[Education Level]]="Bachelor's Degree", "Bachelor's Degree", "Others")) -> Others
A40: EMP-10039 | B40: Trevor Williams | C40: Male | D40: 23 | E40: IT | F40: Head Office | G40: Grade 1 – Entry | H40: Permanent | I40: Professional Certification | J40: 44385 | M40: Active | N40: 3394.86 | O40: MGR-10098 | P40: 4.9 | Q40: =IF(Table1[[#This Row],[Tenure (Years)]]<1,"< 1 Year", IF(Table1[[#This Row],[Tenure (Years)]]<2,"1–2 Years", IF(Table1[[#This Row],[Tenure (Years)]]<3,"2–3 Years", IF(Table1[[#This Row],[Tenure (Years)]]<5,"3–5 Years", IF(Table1[[#This Row],[Tenure (Years)]]<10,"5–10 Years", "> 10 Years"))))) -> 3–5 Years | R40: =YEAR(Table1[[#This Row],[Hire Date]]) -> 2021 | T40: =IF(Table1[[#This Row],[Education Level]]="Master's Degree", "Master's Degree", IF(Table1[[#This Row],[Education Level]]="Bachelor's Degree", "Bachelor's Degree", "Others")) -> Others
A41: EMP-10040 | B41: Kyle Velez | C41: Male | D41: 36 | E41: IT | F41: East Region | G41: Grade 1 – Entry | H41: Permanent | I41: PhD | J41: 45306 | M41: Active | N41: 3154.09 | O41: MGR-10221 | P41: 2.3 | Q41: =IF(Table1[[#This Row],[Tenure (Years)]]<1,"< 1 Year", IF(Table1[[#This Row],[Tenure (Years)]]<2,"1–2 Years", IF(Table1[[#This Row],[Tenure (Years)]]<3,"2–3 Years", IF(Table1[[#This Row],[Tenure (Years)]]<5,"3–5 Years", IF(Table1[[#This Row],[Tenure (Years)]]<10,"5–10 Years", "> 10 Years"))))) -> 2–3 Years | R41: =YEAR(Table1[[#This Row],[Hire Date]]) -> 2024 | T41: =IF(Table1[[#This Row],[Education Level]]="Master's Degree", "Master's Degree", IF(Table1[[#This Row],[Education Level]]="Bachelor's Degree", "Bachelor's Degree", "Others")) -> Others
A42: EMP-10041 | B42: Jaime Lewis | C42: Female | D42: 41 | E42: Human Resources | F42: Head Office | G42: Grade 6 – Manager | H42: Contract | I42: Master's Degree | J42: 45818 | M42: Active | N42: 29207.71 | O42: MGR-10207 | P42: 0.9 | Q42: =IF(Table1[[#This Row],[Tenure (Years)]]<1,"< 1 Year", IF(Table1[[#This Row],[Tenure (Years)]]<2,"1–2 Years", IF(Table1[[#This Row],[Tenure (Years)]]<3,"2–3 Years", IF(Table1[[#This Row],[Tenure (Years)]]<5,"3–5 Years", IF(Table1[[#This Row],[Tenure (Years)]]<10,"5–10 Years", "> 10 Years"))))) -> < 1 Year | R42: =YEAR(Table1[[#This Row],[Hire Date]]) -> 2025 | T42: =IF(Table1[[#This Row],[Education Level]]="Master's Degree", "Master's Degree", IF(Table1[[#This Row],[Education Level]]="Bachelor's Degree", "Bachelor's Degree", "Others")) -> Master's Degree
A43: EMP-10042 | B43: Melinda Richardson | C43: Female | D43: 36 | E43: IT | F43: South Region | G43: Grade 4 – Senior | H43: Permanent | I43: Master's Degree | J43: 44653 | M43: Active | N43: 10363.28 | O43: MGR-10281 | P43: 4.1 | Q43: =IF(Table1[[#This Row],[Tenure (Years)]]<1,"< 1 Year", IF(Table1[[#This Row],[Tenure (Years)]]<2,"1–2 Years", IF(Table1[[#This Row],[Tenure (Years)]]<3,"2–3 Years", IF(Table1[[#This Row],[Tenure (Years)]]<5,"3–5 Years", IF(Table1[[#This Row],[Tenure (Years)]]<10,"5–10 Years", "> 10 Years"))))) -> 3–5 Years | R43: =YEAR(Table1[[#This Row],[Hire Date]]) -> 2022 | T43: =IF(Table1[[#This Row],[Education Level]]="Master's Degree", "Master's Degree", IF(Table1[[#This Row],[Education Level]]="Bachelor's Degree", "Bachelor's Degree", "Others")) -> Master's Degree
A44: EMP-10043 | B44: Heather Hernandez | C44: Female | D44: 33 | E44: Finance | F44: North Region | G44: Grade 3 – Mid-Level | H44: Permanent | I44: Bachelor's Degree | J44: 45585 | M44: Active | N44: 7130.55 | O44: MGR-10243 | P44: 1.6 | Q44: =IF(Table1[[#This Row],[Tenure (Years)]]<1,"< 1 Year", IF(Table1[[#This Row],[Tenure (Years)]]<2,"1–2 Years", IF(Table1[[#This Row],[Tenure (Years)]]<3,"2–3 Years", IF(Table1[[#This Row],[Tenure (Years)]]<5,"3–5 Years", IF(Table1[[#This Row],[Tenure (Years)]]<10,"5–10 Years", "> 10 Years"))))) -> 1–2 Years | R44: =YEAR(Table1[[#This Row],[Hire Date]]) -> 2024 | T44: =IF(Table1[[#This Row],[Education Level]]="Master's Degree", "Master's Degree", IF(Table1[[#This Row],[Education Level]]="Bachelor's Degree", "Bachelor's Degree", "Others")) -> Bachelor's Degree
A45: EMP-10044 | B45: Kimberly Munoz | C45: Female | D45: 32 | E45: Operations | F45: East Region | G45: Grade 3 – Mid-Level | H45: Permanent | I45: Master's Degree | J45: 45637 | M45: Active | N45: 7351.36 | O45: MGR-10116 | P45: 1.4 | Q45: =IF(Table1[[#This Row],[Tenure (Years)]]<1,"< 1 Year", IF(Table1[[#This Row],[Tenure (Years)]]<2,"1–2 Years", IF(Table1[[#This Row],[Tenure (Years)]]<3,"2–3 Years", IF(Table1[[#This Row],[Tenure (Years)]]<5,"3–5 Years", IF(Table1[[#This Row],[Tenure (Years)]]<10,"5–10 Years", "> 10 Years"))))) -> 1–2 Years | R45: =YEAR(Table1[[#This Row],[Hire Date]]) -> 2024 | T45: =IF(Table1[[#This Row],[Education Level]]="Master's Degree", "Master's Degree", IF(Table1[[#This Row],[Education Level]]="Bachelor's Degree", "Bachelor's Degree", "Others")) -> Master's Degree
A46: EMP-10045 | B46: Kara Wolf | C46: Female | D46: 22 | E46: Sales | F46: North Region | G46: Grade 2 – Junior | H46: Contract | I46: Diploma | J46: 45604 | K46: 46173 | L46: End of Contract | M46: Inactive | N46: 4115.53 | O46: MGR-10254 | P46: 1.6 | Q46: =IF(Table1[[#This Row],[Tenure (Years)]]<1,"< 1 Year", IF(Table1[[#This Row],[Tenure (Years)]]<2,"1–2 Years", IF(Table1[[#This Row],[Tenure (Years)]]<3,"2–3 Years", IF(Table1[[#This Row],[Tenure (Years)]]<5,"3–5 Years", IF(Table1[[#This Row],[Tenure (Years)]]<10,"5–10 Years", "> 10 Years"))))) -> 1–2 Years | R46: =YEAR(Table1[[#This Row],[Hire Date]]) -> 2024 | S46: =YEAR(Table1[[#This Row],[Exit Date]]) -> 2026 | T46: =IF(Table1[[#This Row],[Education Level]]="Master's Degree", "Master's Degree", IF(Table1[[#This Row],[Education Level]]="Bachelor's Degree", "Bachelor's Degree", "Others")) -> Others
A47: EMP-10046 | B47: Mark Melton | C47: Male | D47: 28 | E47: Marketing | F47: West Region | G47: Grade 2 – Junior | H47: Contract | I47: Bachelor's Degree | J47: 43537 | M47: Active | N47: 5640.15 | O47: MGR-10286 | P47: 7.2 | Q47: =IF(Table1[[#This Row],[Tenure (Years)]]<1,"< 1 Year", IF(Table1[[#This Row],[Tenure (Years)]]<2,"1–2 Years", IF(Table1[[#This Row],[Tenure (Years)]]<3,"2–3 Years", IF(Table1[[#This Row],[Tenure (Years)]]<5,"3–5 Years", IF(Table1[[#This Row],[Tenure (Years)]]<10,"5–10 Years", "> 10 Years"))))) -> 5–10 Years | R47: =YEAR(Table1[[#This Row],[Hire Date]]) -> 2019 | T47: =IF(Table1[[#This Row],[Education Level]]="Master's Degree", "Master's Degree", IF(Table1[[#This Row],[Education Level]]="Bachelor's Degree", "Bachelor's Degree", "Others")) -> Bachelor's Degree
A48: EMP-10047 | B48: Marvin Benson | C48: Male | D48: 30 | E48: Sales | F48: South Region | G48: Grade 6 – Manager | H48: Permanent | I48: Professional Certification | J48: 45004 | M48: Active | N48: 21213.59 | O48: MGR-10457 | P48: 3.2 | Q48: =IF(Table1[[#This Row],[Tenure (Years)]]<1,"< 1 Year", IF(Table1[[#This Row],[Tenure (Years)]]<2,"1–2 Years", IF(Table1[[#This Row],[Tenure (Years)]]<3,"2–3 Years", IF(Table1[[#This Row],[Tenure (Years)]]<5,"3–5 Years", IF(Table1[[#This Row],[Tenure (Years)]]<10,"5–10 Years", "> 10 Years"))))) -> 3–5 Years | R48: =YEAR(Table1[[#This Row],[Hire Date]]) -> 2023 | T48: =IF(Table1[[#This Row],[Education Level]]="Master's Degree", "Master's Degree", IF(Table1[[#This Row],[Education Level]]="Bachelor's Degree", "Bachelor's Degree", "Others")) -> Others
A49: EMP-10048 | B49: Ronald Mason | C49: Male | D49: 44 | E49: Risk & Compliance | F49: West Region | G49: Grade 4 – Senior | H49: Permanent | I49: Bachelor's Degree | J49: 45345 | M49: Active | N49: 12736.73 | O49: MGR-10385 | P49: 2.2 | Q49: =IF(Table1[[#This Row],[Tenure (Years)]]<1,"< 1 Year", IF(Table1[[#This Row],[Tenure (Years)]]<2,"1–2 Years", IF(Table1[[#This Row],[Tenure (Years)]]<3,"2–3 Years", IF(Table1[[#This Row],[Tenure (Years)]]<5,"3–5 Years", IF(Table1[[#This Row],[Tenure (Years)]]<10,"5–10 Years", "> 10 Years"))))) -> 2–3 Years | R49: =YEAR(Table1[[#This Row],[Hire Date]]) -> 2024 | T49: =IF(Table1[[#This Row],[Education Level]]="Master's Degree", "Master's Degree", IF(Table1[[#This Row],[Education Level]]="Bachelor's Degree", "Bachelor's Degree", "Others")) -> Bachelor's Degree
A50: EMP-10049 | B50: Lindsey Morrow | C50: Female | D50: 38 | E50: Sales | F50: Head Office | G50: Grade 5 – Lead | H50: Permanent | I50: Bachelor's Degree | J50: 45085 | M50: Active | N50: 15663.87 | O50: MGR-10140 | P50: 2.9 | Q50: =IF(Table1[[#This Row],[Tenure (Years)]]<1,"< 1 Year", IF(Table1[[#This Row],[Tenure (Years)]]<2,"1–2 Years", IF(Table1[[#This Row],[Tenure (Years)]]<3,"2–3 Years", IF(Table1[[#This Row],[Tenure (Years)]]<5,"3–5 Years", IF(Table1[[#This Row],[Tenure (Years)]]<10,"5–10 Years", "> 10 Years"))))) -> 2–3 Years | R50: =YEAR(Table1[[#This Row],[Hire Date]]) -> 2023 | T50: =IF(Table1[[#This Row],[Education Level]]="Master's Degree", "Master's Degree", IF(Table1[[#This Row],[Education Level]]="Bachelor's Degree", "Bachelor's Degree", "Others")) -> Bachelor's Degree
A51: EMP-10050 | B51: Anthony Alexander | C51: Male | D51: 22 | E51: Legal | F51: Head Office | G51: Grade 3 – Mid-Level | H51: Permanent | I51: Bachelor's Degree | J51: 44048 | M51: Active | N51: 8120.46 | O51: MGR-10170 | P51: 5.8 | Q51: =IF(Table1[[#This Row],[Tenure (Years)]]<1,"< 1 Year", IF(Table1[[#This Row],[Tenure (Years)]]<2,"1–2 Years", IF(Table1[[#This Row],[Tenure (Years)]]<3,"2–3 Years", IF(Table1[[#This Row],[Tenure (Years)]]<5,"3–5 Years", IF(Table1[[#This Row],[Tenure (Years)]]<10,"5–10 Years", "> 10 Years"))))) -> 5–10 Years | R51: =YEAR(Table1[[#This Row],[Hire Date]]) -> 2020 | T51: =IF(Table1[[#This Row],[Education Level]]="Master's Degree", "Master's Degree", IF(Table1[[#This Row],[Education Level]]="Bachelor's Degree", "Bachelor's Degree", "Others")) -> Bachelor's Degree
A52: EMP-10051 | B52: Mindy Anderson | C52: Female | D52: 37 | E52: Customer Service | F52: East Region | G52: Grade 2 – Junior | H52: Internship | I52: Bachelor's Degree | J52: 44696 | M52: Active | N52: 4155.66 | O52: MGR-10195 | P52: 4 | Q52: =IF(Table1[[#This Row],[Tenure (Years)]]<1,"< 1 Year", IF(Table1[[#This Row],[Tenure (Years)]]<2,"1–2 Years", IF(Table1[[#This Row],[Tenure (Years)]]<3,"2–3 Years", IF(Table1[[#This Row],[Tenure (Years)]]<5,"3–5 Years", IF(Table1[[#This Row],[Tenure (Years)]]<10,"5–10 Years", "> 10 Years"))))) -> 3–5 Years | R52: =YEAR(Table1[[#This Row],[Hire Date]]) -> 2022 | T52: =IF(Table1[[#This Row],[Education Level]]="Master's Degree", "Master's Degree", IF(Table1[[#This Row],[Education Level]]="Bachelor's Degree", "Bachelor's Degree", "Others")) -> Bachelor's Degree
A53: EMP-10052 | B53: Diane Johnson | C53: Female | D53: 31 | E53: Risk & Compliance | F53: West Region | G53: Grade 1 – Entry | H53: Permanent | I53: Master's Degree | J53: 44817 | M53: Active | N53: 3027.64 | O53: MGR-10250 | P53: 3.7 | Q53: =IF(Table1[[#This Row],[Tenure (Years)]]<1,"< 1 Year", IF(Table1[[#This Row],[Tenure (Years)]]<2,"1–2 Years", IF(Table1[[#This Row],[Tenure (Years)]]<3,"2–3 Years", IF(Table1[[#This Row],[Tenure (Years)]]<5,"3–5 Years", IF(Table1[[#This Row],[Tenure (Years)]]<10,"5–10 Years", "> 10 Years"))))) -> 3–5 Years | R53: =YEAR(Table1[[#This Row],[Hire Date]]) -> 2022 | T53: =IF(Table1[[#This Row],[Education Level]]="Master's Degree", "Master's Degree", IF(Table1[[#This Row],[Education Level]]="Bachelor's Degree", "Bachelor's Degree", "Others")) -> Master's Degree
A54: EMP-10053 | B54: Larry Reese | C54: Male | D54: 28 | E54: Sales | F54: Head Office | G54: Grade 2 – Junior | H54: Permanent | I54: Bachelor's Degree | J54: 45840 | M54: Active | N54: 5214.1 | O54: MGR-10066 | P54: 0.9 | Q54: =IF(Table1[[#This Row],[Tenure (Years)]]<1,"< 1 Year", IF(Table1[[#This Row],[Tenure (Years)]]<2,"1–2 Years", IF(Table1[[#This Row],[Tenure (Years)]]<3,"2–3 Years", IF(Table1[[#This Row],[Tenure (Years)]]<5,"3–5 Years", IF(Table1[[#This Row],[Tenure (Years)]]<10,"5–10 Years", "> 10 Years"))))) -> < 1 Year | R54: =YEAR(Table1[[#This Row],[Hire Date]]) -> 2025 | T54: =IF(Table1[[#This Row],[Education Level]]="Master's Degree", "Master's Degree", IF(Table1[[#This Row],[Education Level]]="Bachelor's Degree", "Bachelor's Degree", "Others")) -> Bachelor's Degree
A55: EMP-10054 | B55: Tina Woodard | C55: Female | D55: 40 | E55: Procurement | F55: Head Office | G55: Grade 3 – Mid-Level | H55: Permanent | I55: Bachelor's Degree | J55: 45816 | M55: Active | N55: 9220.79 | O55: MGR-10026 | P55: 0.9 | Q55: =IF(Table1[[#This Row],[Tenure (Years)]]<1,"< 1 Year", IF(Table1[[#This Row],[Tenure (Years)]]<2,"1–2 Years", IF(Table1[[#This Row],[Tenure (Years)]]<3,"2–3 Years", IF(Table1[[#This Row],[Tenure (Years)]]<5,"3–5 Years", IF(Table1[[#This Row],[Tenure (Years)]]<10,"5–10 Years", "> 10 Years"))))) -> < 1 Year | R55: =YEAR(Table1[[#This Row],[Hire Date]]) -> 2025 | T55: =IF(Table1[[#This Row],[Education Level]]="Master's Degree", "Master's Degree", IF(Table1[[#This Row],[Education Level]]="Bachelor's Degree", "Bachelor's Degree", "Others")) -> Bachelor's Degree
A56: EMP-10055 | B56: Gary Johnston | C56: Male | D56: 44 | E56: IT | F56: North Region | G56: Grade 3 – Mid-Level | H56: Permanent | I56: PhD | J56: 44653 | M56: Active | N56: 7134.98 | O56: MGR-10241 | P56: 4.1 | Q56: =IF(Table1[[#This Row],[Tenure (Years)]]<1,"< 1 Year", IF(Table1[[#This Row],[Tenure (Years)]]<2,"1–2 Years", IF(Table1[[#This Row],[Tenure (Years)]]<3,"2–3 Years", IF(Table1[[#This Row],[Tenure (Years)]]<5,"3–5 Years", IF(Table1[[#This Row],[Tenure (Years)]]<10,"5–10 Years", "> 10 Years"))))) -> 3–5 Years | R56: =YEAR(Table1[[#This Row],[Hire Date]]) -> 2022 | T56: =IF(Table1[[#This Row],[Education Level]]="Master's Degree", "Master's Degree", IF(Table1[[#This Row],[Education Level]]="Bachelor's Degree", "Bachelor's Degree", "Others")) -> Others
A57: EMP-10056 | B57: Tammy Wise | C57: Female | D57: 43 | E57: Finance | F57: East Region | G57: Grade 5 – Lead | H57: Permanent | I57: Master's Degree | J57: 44019 | M57: Active | N57: 14312.51 | O57: MGR-10487 | P57: 5.9 | Q57: =IF(Table1[[#This Row],[Tenure (Years)]]<1,"< 1 Year", IF(Table1[[#This Row],[Tenure (Years)]]<2,"1–2 Years", IF(Table1[[#This Row],[Tenure (Years)]]<3,"2–3 Years", IF(Table1[[#This Row],[Tenure (Years)]]<5,"3–5 Years", IF(Table1[[#This Row],[Tenure (Years)]]<10,"5–10 Years", "> 10 Years"))))) -> 5–10 Years | R57: =YEAR(Table1[[#This Row],[Hire Date]]) -> 2020 | T57: =IF(Table1[[#This Row],[Education Level]]="Master's Degree", "Master's Degree", IF(Table1[[#This Row],[Education Level]]="Bachelor's Degree", "Bachelor's Degree", "Others")) -> Master's Degree
A58: EMP-10057 | B58: Troy Taylor | C58: Male | D58: 27 | E58: Sales | F58: Central Hub | G58: Grade 2 – Junior | H58: Permanent | I58: Diploma | J58: 43618 | M58: Active | N58: 4050.95 | O58: MGR-10132 | P58: 7 | Q58: =IF(Table1[[#This Row],[Tenure (Years)]]<1,"< 1 Year", IF(Table1[[#This Row],[Tenure (Years)]]<2,"1–2 Years", IF(Table1[[#This Row],[Tenure (Years)]]<3,"2–3 Years", IF(Table1[[#This Row],[Tenure (Years)]]<5,"3–5 Years", IF(Table1[[#This Row],[Tenure (Years)]]<10,"5–10 Years", "> 10 Years"))))) -> 5–10 Years | R58: =YEAR(Table1[[#This Row],[Hire Date]]) -> 2019 | T58: =IF(Table1[[#This Row],[Education Level]]="Master's Degree", "Master's Degree", IF(Table1[[#This Row],[Education Level]]="Bachelor's Degree", "Bachelor's Degree", "Others")) -> Others
A59: EMP-10058 | B59: Jessica Wright | C59: Female | D59: 32 | E59: Legal | F59: Head Office | G59: Grade 3 – Mid-Level | H59: Contract | I59: Bachelor's Degree | J59: 43570 | M59: Active | N59: 8321.74 | O59: MGR-10295 | P59: 7.1 | Q59: =IF(Table1[[#This Row],[Tenure (Years)]]<1,"< 1 Year", IF(Table1[[#This Row],[Tenure (Years)]]<2,"1–2 Years", IF(Table1[[#This Row],[Tenure (Years)]]<3,"2–3 Years", IF(Table1[[#This Row],[Tenure (Years)]]<5,"3–5 Years", IF(Table1[[#This Row],[Tenure (Years)]]<10,"5–10 Years", "> 10 Years"))))) -> 5–10 Years | R59: =YEAR(Table1[[#This Row],[Hire Date]]) -> 2019 | T59: =IF(Table1[[#This Row],[Education Level]]="Master's Degree", "Master's Degree", IF(Table1[[#This Row],[Education Level]]="Bachelor's Degree", "Bachelor's Degree", "Others")) -> Bachelor's Degree
A60: EMP-10059 | B60: Shannon Hall | C60: Female | D60: 37 | E60: Executive Management | F60: South Region | G60: Grade 8 – Executive | H60: Permanent | I60: Master's Degree | J60: 43913 | K60: 46083 | L60: Resignation | M60: Inactive | N60: 54382.67 | O60: N/A | P60: 5.9 | Q60: =IF(Table1[[#This Row],[Tenure (Years)]]<1,"< 1 Year", IF(Table1[[#This Row],[Tenure (Years)]]<2,"1–2 Years", IF(Table1[[#This Row],[Tenure (Years)]]<3,"2–3 Years", IF(Table1[[#This Row],[Tenure (Years)]]<5,"3–5 Years", IF(Table1[[#This Row],[Tenure (Years)]]<10,"5–10 Years", "> 10 Years"))))) -> 5–10 Years | R60: =YEAR(Table1[[#This Row],[Hire Date]]) -> 2020 | S60: =YEAR(Table1[[#This Row],[Exit Date]]) -> 2026 | T60: =IF(Table1[[#This Row],[Education Level]]="Master's Degree", "Master's Degree", IF(Table1[[#This Row],[Education Level]]="Bachelor's Degree", "Bachelor's Degree", "Others")) -> Master's Degree
A61: EMP-10060 | B61: Priscilla Garcia | C61: Female | D61: 43 | E61: Executive Management | F61: North Region | G61: Grade 7 – Director | H61: Permanent | I61: Bachelor's Degree | J61: 43269 | M61: Active | N61: 31815.83 | O61: N/A | P61: 7.9 | Q61: =IF(Table1[[#This Row],[Tenure (Years)]]<1,"< 1 Year", IF(Table1[[#This Row],[Tenure (Years)]]<2,"1–2 Years", IF(Table1[[#This Row],[Tenure (Years)]]<3,"2–3 Years", IF(Table1[[#This Row],[Tenure (Years)]]<5,"3–5 Years", IF(Table1[[#This Row],[Tenure (Years)]]<10,"5–10 Years", "> 10 Years"))))) -> 5–10 Years | R61: =YEAR(Table1[[#This Row],[Hire Date]]) -> 2018 | T61: =IF(Table1[[#This Row],[Education Level]]="Master's Degree", "Master's Degree", IF(Table1[[#This Row],[Education Level]]="Bachelor's Degree", "Bachelor's Degree", "Others")) -> Bachelor's Degree
A62: EMP-10061 | B62: Daniel Peterson | C62: Male | D62: 30 | E62: Legal | F62: West Region | G62: Grade 1 – Entry | H62: Part-Time | I62: Bachelor's Degree | J62: 44876 | M62: Active | N62: 3130.09 | O62: MGR-10223 | P62: 3.5 | Q62: =IF(Table1[[#This Row],[Tenure (Years)]]<1,"< 1 Year", IF(Table1[[#This Row],[Tenure (Years)]]<2,"1–2 Years", IF(Table1[[#This Row],[Tenure (Years)]]<3,"2–3 Years", IF(Table1[[#This Row],[Tenure (Years)]]<5,"3–5 Years", IF(Table1[[#This Row],[Tenure (Years)]]<10,"5–10 Years", "> 10 Years"))))) -> 3–5 Years | R62: =YEAR(Table1[[#This Row],[Hire Date]]) -> 2022 | T62: =IF(Table1[[#This Row],[Education Level]]="Master's Degree", "Master's Degree", IF(Table1[[#This Row],[Education Level]]="Bachelor's Degree", "Bachelor's Degree", "Others")) -> Bachelor's Degree
A63: EMP-10062 | B63: Evan Mcconnell | C63: Male | D63: 33 | E63: Operations | F63: West Region | G63: Grade 4 – Senior | H63: Contract | I63: Bachelor's Degree | J63: 45305 | M63: Active | N63: 13844.63 | O63: MGR-10126 | P63: 2.3 | Q63: =IF(Table1[[#This Row],[Tenure (Years)]]<1,"< 1 Year", IF(Table1[[#This Row],[Tenure (Years)]]<2,"1–2 Years", IF(Table1[[#This Row],[Tenure (Years)]]<3,"2–3 Years", IF(Table1[[#This Row],[Tenure (Years)]]<5,"3–5 Years", IF(Table1[[#This Row],[Tenure (Years)]]<10,"5–10 Years", "> 10 Years"))))) -> 2–3 Years | R63: =YEAR(Table1[[#This Row],[Hire Date]]) -> 2024 | T63: =IF(Table1[[#This Row],[Education Level]]="Master's Degree", "Master's Degree", IF(Table1[[#This Row],[Education Level]]="Bachelor's Degree", "Bachelor's Degree", "Others")) -> Bachelor's Degree
A64: EMP-10063 | B64: Elizabeth Mcclure | C64: Female | D64: 25 | E64: Human Resources | F64: Head Office | G64: Grade 2 – Junior | H64: Permanent | I64: Bachelor's Degree | J64: 45435 | M64: Active | N64: 5127.01 | O64: MGR-10094 | P64: 2 | Q64: =IF(Table1[[#This Row],[Tenure (Years)]]<1,"< 1 Year", IF(Table1[[#This Row],[Tenure (Years)]]<2,"1–2 Years", IF(Table1[[#This Row],[Tenure (Years)]]<3,"2–3 Years", IF(Table1[[#This Row],[Tenure (Years)]]<5,"3–5 Years", IF(Table1[[#This Row],[Tenure (Years)]]<10,"5–10 Years", "> 10 Years"))))) -> 2–3 Years | R64: =YEAR(Table1[[#This Row],[Hire Date]]) -> 2024 | T64: =IF(Table1[[#This Row],[Education Level]]="Master's Degree", "Master's Degree", IF(Table1[[#This Row],[Education Level]]="Bachelor's Degree", "Bachelor's Degree", "Others")) -> Bachelor's Degree
A65: EMP-10064 | B65: Johnny Swanson | C65: Male | D65: 24 | E65: Risk & Compliance | F65: Head Office | G65: Grade 3 – Mid-Level | H65: Permanent | I65: Bachelor's Degree | J65: 45542 | M65: Active | N65: 8893.5 | O65: MGR-10044 | P65: 1.7 | Q65: =IF(Table1[[#This Row],[Tenure (Years)]]<1,"< 1 Year", IF(Table1[[#This Row],[Tenure (Years)]]<2,"1–2 Years", IF(Table1[[#This Row],[Tenure (Years)]]<3,"2–3 Years", IF(Table1[[#This Row],[Tenure (Years)]]<5,"3–5 Years", IF(Table1[[#This Row],[Tenure (Years)]]<10,"5–10 Years", "> 10 Years"))))) -> 1–2 Years | R65: =YEAR(Table1[[#This Row],[Hire Date]]) -> 2024 | T65: =IF(Table1[[#This Row],[Education Level]]="Master's Degree", "Master's Degree", IF(Table1[[#This Row],[Education Level]]="Bachelor's Degree", "Bachelor's Degree", "Others")) -> Bachelor's Degree
A66: EMP-10065 | B66: Michele Ferguson | C66: Female | D66: 42 | E66: Sales | F66: North Region | G66: Grade 4 – Senior | H66: Permanent | I66: Master's Degree | J66: 45929 | K66: 46094 | L66: Resignation | M66: Inactive | N66: 11698.6 | O66: MGR-10355 | P66: 0.5 | Q66: =IF(Table1[[#This Row],[Tenure (Years)]]<1,"< 1 Year", IF(Table1[[#This Row],[Tenure (Years)]]<2,"1–2 Years", IF(Table1[[#This Row],[Tenure (Years)]]<3,"2–3 Years", IF(Table1[[#This Row],[Tenure (Years)]]<5,"3–5 Years", IF(Table1[[#This Row],[Tenure (Years)]]<10,"5–10 Years", "> 10 Years"))))) -> < 1 Year | R66: =YEAR(Table1[[#This Row],[Hire Date]]) -> 2025 | S66: =YEAR(Table1[[#This Row],[Exit Date]]) -> 2026 | T66: =IF(Table1[[#This Row],[Education Level]]="Master's Degree", "Master's Degree", IF(Table1[[#This Row],[Education Level]]="Bachelor's Degree", "Bachelor's Degree", "Others")) -> Master's Degree
A67: EMP-10066 | B67: Michael Branch | C67: Male | D67: 47 | E67: Sales | F67: South Region | G67: Grade 2 – Junior | H67: Permanent | I67: Professional Certification | J67: 45275 | M67: Active | N67: 5453.89 | O67: MGR-10233 | P67: 2.4 | Q67: =IF(Table1[[#This Row],[Tenure (Years)]]<1,"< 1 Year", IF(Table1[[#This Row],[Tenure (Years)]]<2,"1–2 Years", IF(Table1[[#This Row],[Tenure (Years)]]<3,"2–3 Years", IF(Table1[[#This Row],[Tenure (Years)]]<5,"3–5 Years", IF(Table1[[#This Row],[Tenure (Years)]]<10,"5–10 Years", "> 10 Years"))))) -> 2–3 Years | R67: =YEAR(Table1[[#This Row],[Hire Date]]) -> 2023 | T67: =IF(Table1[[#This Row],[Education Level]]="Master's Degree", "Master's Degree", IF(Table1[[#This Row],[Education Level]]="Bachelor's Degree", "Bachelor's Degree", "Others")) -> Others
A68: EMP-10067 | B68: Ashley Cabrera | C68: Female | D68: 34 | E68: IT | F68: East Region | G68: Grade 3 – Mid-Level | H68: Permanent | I68: Bachelor's Degree | J68: 44393 | M68: Active | N68: 7191.61 | O68: MGR-10111 | P68: 4.8 | Q68: =IF(Table1[[#This Row],[Tenure (Years)]]<1,"< 1 Year", IF(Table1[[#This Row],[Tenure (Years)]]<2,"1–2 Years", IF(Table1[[#This Row],[Tenure (Years)]]<3,"2–3 Years", IF(Table1[[#This Row],[Tenure (Years)]]<5,"3–5 Years", IF(Table1[[#This Row],[Tenure (Years)]]<10,"5–10 Years", "> 10 Years"))))) -> 3–5 Years | R68: =YEAR(Table1[[#This Row],[Hire Date]]) -> 2021 | T68: =IF(Table1[[#This Row],[Education Level]]="Master's Degree", "Master's Degree", IF(Table1[[#This Row],[Education Level]]="Bachelor's Degree", "Bachelor's Degree", "Others")) -> Bachelor's Degree
A69: EMP-10068 | B69: Kristen Griffin | C69: Female | D69: 44 | E69: Risk & Compliance | F69: Head Office | G69: Grade 3 – Mid-Level | H69: Permanent | I69: Diploma | J69: 45545 | M69: Active | N69: 8268.76 | O69: MGR-10092 | P69: 1.7 | Q69: =IF(Table1[[#This Row],[Tenure (Years)]]<1,"< 1 Year", IF(Table1[[#This Row],[Tenure (Years)]]<2,"1–2 Years", IF(Table1[[#This Row],[Tenure (Years)]]<3,"2–3 Years", IF(Table1[[#This Row],[Tenure (Years)]]<5,"3–5 Years", IF(Table1[[#This Row],[Tenure (Years)]]<10,"5–10 Years", "> 10 Years"))))) -> 1–2 Years | R69: =YEAR(Table1[[#This Row],[Hire Date]]) -> 2024 | T69: =IF(Table1[[#This Row],[Education Level]]="Master's Degree", "Master's Degree", IF(Table1[[#This Row],[Education Level]]="Bachelor's Degree", "Bachelor's Degree", "Others")) -> Others
A70: EMP-10069 | B70: Troy Patterson | C70: Male | D70: 38 | E70: IT | F70: Head Office | G70: Grade 1 – Entry | H70: Permanent | I70: Master's Degree | J70: 43324 | M70: Active | N70: 3301.2 | O70: MGR-10252 | P70: 7.8 | Q70: =IF(Table1[[#This Row],[Tenure (Years)]]<1,"< 1 Year", IF(Table1[[#This Row],[Tenure (Years)]]<2,"1–2 Years", IF(Table1[[#This Row],[Tenure (Years)]]<3,"2–3 Years", IF(Table1[[#This Row],[Tenure (Years)]]<5,"3–5 Years", IF(Table1[[#This Row],[Tenure (Years)]]<10,"5–10 Years", "> 10 Years"))))) -> 5–10 Years | R70: =YEAR(Table1[[#This Row],[Hire Date]]) -> 2018 | T70: =IF(Table1[[#This Row],[Education Level]]="Master's Degree", "Master's Degree", IF(Table1[[#This Row],[Education Level]]="Bachelor's Degree", "Bachelor's Degree", "Others")) -> Master's Degree
A71: EMP-10070 | B71: Mark Hopkins | C71: Male | D71: 29 | E71: Human Resources | F71: Head Office | G71: Grade 5 – Lead | H71: Permanent | I71: PhD | J71: 44905 | M71: Active | N71: 17444.39 | O71: MGR-10059 | P71: 3.4 | Q71: =IF(Table1[[#This Row],[Tenure (Years)]]<1,"< 1 Year", IF(Table1[[#This Row],[Tenure (Years)]]<2,"1–2 Years", IF(Table1[[#This Row],[Tenure (Years)]]<3,"2–3 Years", IF(Table1[[#This Row],[Tenure (Years)]]<5,"3–5 Years", IF(Table1[[#This Row],[Tenure (Years)]]<10,"5–10 Years", "> 10 Years"))))) -> 3–5 Years | R71: =YEAR(Table1[[#This Row],[Hire Date]]) -> 2022 | T71: =IF(Table1[[#This Row],[Education Level]]="Master's Degree", "Master's Degree", IF(Table1[[#This Row],[Education Level]]="Bachelor's Degree", "Bachelor's Degree", "Others")) -> Others
A72: EMP-10071 | B72: Cynthia Ferguson | C72: Female | D72: 38 | E72: Human Resources | F72: Central Hub | G72: Grade 3 – Mid-Level | H72: Permanent | I72: Master's Degree | J72: 43320 | K72: 45546 | L72: Resignation | M72: Inactive | N72: 6722.25 | O72: MGR-10392 | P72: 6.1 | Q72: =IF(Table1[[#This Row],[Tenure (Years)]]<1,"< 1 Year", IF(Table1[[#This Row],[Tenure (Years)]]<2,"1–2 Years", IF(Table1[[#This Row],[Tenure (Years)]]<3,"2–3 Years", IF(Table1[[#This Row],[Tenure (Years)]]<5,"3–5 Years", IF(Table1[[#This Row],[Tenure (Years)]]<10,"5–10 Years", "> 10 Years"))))) -> 5–10 Years | R72: =YEAR(Table1[[#This Row],[Hire Date]]) -> 2018 | S72: =YEAR(Table1[[#This Row],[Exit Date]]) -> 2024 | T72: =IF(Table1[[#This Row],[Education Level]]="Master's Degree", "Master's Degree", IF(Table1[[#This Row],[Education Level]]="Bachelor's Degree", "Bachelor's Degree", "Others")) -> Master's Degree
A73: EMP-10072 | B73: Ryan Molina | C73: Male | D73: 48 | E73: Marketing | F73: Head Office | G73: Grade 4 – Senior | H73: Permanent | I73: Master's Degree | J73: 45241 | M73: Active | N73: 13058.33 | O73: MGR-10220 | P73: 2.5 | Q73: =IF(Table1[[#This Row],[Tenure (Years)]]<1,"< 1 Year", IF(Table1[[#This Row],[Tenure (Years)]]<2,"1–2 Years", IF(Table1[[#This Row],[Tenure (Years)]]<3,"2–3 Years", IF(Table1[[#This Row],[Tenure (Years)]]<5,"3–5 Years", IF(Table1[[#This Row],[Tenure (Years)]]<10,"5–10 Years", "> 10 Years"))))) -> 2–3 Years | R73: =YEAR(Table1[[#This Row],[Hire Date]]) -> 2023 | T73: =IF(Table1[[#This Row],[Education Level]]="Master's Degree", "Master's Degree", IF(Table1[[#This Row],[Education Level]]="Bachelor's Degree", "Bachelor's Degree", "Others")) -> Master's Degree
A74: EMP-10073 | B74: Elizabeth Hale | C74: Female | D74: 34 | E74: IT | F74: Head Office | G74: Grade 4 – Senior | H74: Internship | I74: Bachelor's Degree | J74: 43507 | K74: 43685 | L74: End of Contract | M74: Inactive | N74: 9771.04 | O74: MGR-10283 | P74: 0.5 | Q74: =IF(Table1[[#This Row],[Tenure (Years)]]<1,"< 1 Year", IF(Table1[[#This Row],[Tenure (Years)]]<2,"1–2 Years", IF(Table1[[#This Row],[Tenure (Years)]]<3,"2–3 Years", IF(Table1[[#This Row],[Tenure (Years)]]<5,"3–5 Years", IF(Table1[[#This Row],[Tenure (Years)]]<10,"5–10 Years", "> 10 Years"))))) -> < 1 Year | R74: =YEAR(Table1[[#This Row],[Hire Date]]) -> 2019 | S74: =YEAR(Table1[[#This Row],[Exit Date]]) -> 2019 | T74: =IF(Table1[[#This Row],[Education Level]]="Master's Degree", "Master's Degree", IF(Table1[[#This Row],[Education Level]]="Bachelor's Degree", "Bachelor's Degree", "Others")) -> Bachelor's Degree
A75: EMP-10074 | B75: Laura Bennett | C75: Female | D75: 49 | E75: Human Resources | F75: East Region | G75: Grade 2 – Junior | H75: Permanent | I75: Bachelor's Degree | J75: 45025 | M75: Active | N75: 5021.29 | O75: MGR-10233 | P75: 3.1 | Q75: =IF(Table1[[#This Row],[Tenure (Years)]]<1,"< 1 Year", IF(Table1[[#This Row],[Tenure (Years)]]<2,"1–2 Years", IF(Table1[[#This Row],[Tenure (Years)]]<3,"2–3 Years", IF(Table1[[#This Row],[Tenure (Years)]]<5,"3–5 Years", IF(Table1[[#This Row],[Tenure (Years)]]<10,"5–10 Years", "> 10 Years"))))) -> 3–5 Years | R75: =YEAR(Table1[[#This Row],[Hire Date]]) -> 2023 | T75: =IF(Table1[[#This Row],[Education Level]]="Master's Degree", "Master's Degree", IF(Table1[[#This Row],[Education Level]]="Bachelor's Degree", "Bachelor's Degree", "Others")) -> Bachelor's Degree
A76: EMP-10075 | B76: Hailey Mccarthy | C76: Female | D76: 22 | E76: Human Resources | F76: Head Office | G76: Grade 4 – Senior | H76: Permanent | I76: Master's Degree | J76: 45661 | K76: 45866 | L76: End of Contract | M76: Inactive | N76: 13657.6 | O76: MGR-10466 | P76: 0.6 | Q76: =IF(Table1[[#This Row],[Tenure (Years)]]<1,"< 1 Year", IF(Table1[[#This Row],[Tenure (Years)]]<2,"1–2 Years", IF(Table1[[#This Row],[Tenure (Years)]]<3,"2–3 Years", IF(Table1[[#This Row],[Tenure (Years)]]<5,"3–5 Years", IF(Table1[[#This Row],[Tenure (Years)]]<10,"5–10 Years", "> 10 Years"))))) -> < 1 Year | R76: =YEAR(Table1[[#This Row],[Hire Date]]) -> 2025 | S76: =YEAR(Table1[[#This Row],[Exit Date]]) -> 2025 | T76: =IF(Table1[[#This Row],[Education Level]]="Master's Degree", "Master's Degree", IF(Table1[[#This Row],[Education Level]]="Bachelor's Degree", "Bachelor's Degree", "Others")) -> Master's Degree
A77: EMP-10076 | B77: Andrew Young | C77: Male | D77: 42 | E77: IT | F77: Central Hub | G77: Grade 5 – Lead | H77: Permanent | I77: Master's Degree | J77: 44360 | M77: Active | N77: 14428.46 | O77: MGR-10240 | P77: 4.9 | Q77: =IF(Table1[[#This Row],[Tenure (Years)]]<1,"< 1 Year", IF(Table1[[#This Row],[Tenure (Years)]]<2,"1–2 Years", IF(Table1[[#This Row],[Tenure (Years)]]<3,"2–3 Years", IF(Table1[[#This Row],[Tenure (Years)]]<5,"3–5 Years", IF(Table1[[#This Row],[Tenure (Years)]]<10,"5–10 Years", "> 10 Years"))))) -> 3–5 Years | R77: =YEAR(Table1[[#This Row],[Hire Date]]) -> 2021 | T77: =IF(Table1[[#This Row],[Education Level]]="Master's Degree", "Master's Degree", IF(Table1[[#This Row],[Education Level]]="Bachelor's Degree", "Bachelor's Degree", "Others")) -> Master's Degree
A78: EMP-10077 | B78: Lawrence Chapman | C78: Male | D78: 35 | E78: IT | F78: West Region | G78: Grade 4 – Senior | H78: Permanent | I78: Bachelor's Degree | J78: 45123 | M78: Active | N78: 13742.04 | O78: MGR-10310 | P78: 2.8 | Q78: =IF(Table1[[#This Row],[Tenure (Years)]]<1,"< 1 Year", IF(Table1[[#This Row],[Tenure (Years)]]<2,"1–2 Years", IF(Table1[[#This Row],[Tenure (Years)]]<3,"2–3 Years", IF(Table1[[#This Row],[Tenure (Years)]]<5,"3–5 Years", IF(Table1[[#This Row],[Tenure (Years)]]<10,"5–10 Years", "> 10 Years"))))) -> 2–3 Years | R78: =YEAR(Table1[[#This Row],[Hire Date]]) -> 2023 | T78: =IF(Table1[[#This Row],[Education Level]]="Master's Degree", "Master's Degree", IF(Table1[[#This Row],[Education Level]]="Bachelor's Degree", "Bachelor's Degree", "Others")) -> Bachelor's Degree
A79: EMP-10078 | B79: Rebecca Simpson | C79: Female | D79: 32 | E79: IT | F79: East Region | G79: Grade 1 – Entry | H79: Permanent | I79: High School | J79: 45457 | M79: Active | N79: 2843.39 | O79: MGR-10296 | P79: 1.9 | Q79: =IF(Table1[[#This Row],[Tenure (Years)]]<1,"< 1 Year", IF(Table1[[#This Row],[Tenure (Years)]]<2,"1–2 Years", IF(Table1[[#This Row],[Tenure (Years)]]<3,"2–3 Years", IF(Table1[[#This Row],[Tenure (Years)]]<5,"3–5 Years", IF(Table1[[#This Row],[Tenure (Years)]]<10,"5–10 Years", "> 10 Years"))))) -> 1–2 Years | R79: =YEAR(Table1[[#This Row],[Hire Date]]) -> 2024 | T79: =IF(Table1[[#This Row],[Education Level]]="Master's Degree", "Master's Degree", IF(Table1[[#This Row],[Education Level]]="Bachelor's Degree", "Bachelor's Degree", "Others")) -> Others
A80: EMP-10079 | B80: Lawrence Huber | C80: Male | D80: 35 | E80: Finance | F80: South Region | G80: Grade 5 – Lead | H80: Internship | I80: Bachelor's Degree | J80: 44912 | K80: 45048 | L80: End of Contract | M80: Inactive | N80: 15051.14 | O80: MGR-10241 | P80: 0.4 | Q80: =IF(Table1[[#This Row],[Tenure (Years)]]<1,"< 1 Year", IF(Table1[[#This Row],[Tenure (Years)]]<2,"1–2 Years", IF(Table1[[#This Row],[Tenure (Years)]]<3,"2–3 Years", IF(Table1[[#This Row],[Tenure (Years)]]<5,"3–5 Years", IF(Table1[[#This Row],[Tenure (Years)]]<10,"5–10 Years", "> 10 Years"))))) -> < 1 Year | R80: =YEAR(Table1[[#This Row],[Hire Date]]) -> 2022 | S80: =YEAR(Table1[[#This Row],[Exit Date]]) -> 2023 | T80: =IF(Table1[[#This Row],[Education Level]]="Master's Degree", "Master's Degree", IF(Table1[[#This Row],[Education Level]]="Bachelor's Degree", "Bachelor's Degree", "Others")) -> Bachelor's Degree
A81: EMP-10080 | B81: Carlos Diaz | C81: Male | D81: 22 | E81: Legal | F81: Head Office | G81: Grade 4 – Senior | H81: Permanent | I81: Master's Degree | J81: 43759 | M81: Active | N81: 10944.76 | O81: MGR-10417 | P81: 6.6 | Q81: =IF(Table1[[#This Row],[Tenure (Years)]]<1,"< 1 Year", IF(Table1[[#This Row],[Tenure (Years)]]<2,"1–2 Years", IF(Table1[[#This Row],[Tenure (Years)]]<3,"2–3 Years", IF(Table1[[#This Row],[Tenure (Years)]]<5,"3–5 Years", IF(Table1[[#This Row],[Tenure (Years)]]<10,"5–10 Years", "> 10 Years"))))) -> 5–10 Years | R81: =YEAR(Table1[[#This Row],[Hire Date]]) -> 2019 | T81: =IF(Table1[[#This Row],[Education Level]]="Master's Degree", "Master's Degree", IF(Table1[[#This Row],[Education Level]]="Bachelor's Degree", "Bachelor's Degree", "Others")) -> Master's Degree
A82: EMP-10081 | B82: Patrick Watson | C82: Male | D82: 33 | E82: Customer Service | F82: South Region | G82: Grade 1 – Entry | H82: Part-Time | I82: Bachelor's Degree | J82: 43575 | M82: Active | N82: 2632.09 | O82: MGR-10337 | P82: 7.1 | Q82: =IF(Table1[[#This Row],[Tenure (Years)]]<1,"< 1 Year", IF(Table1[[#This Row],[Tenure (Years)]]<2,"1–2 Years", IF(Table1[[#This Row],[Tenure (Years)]]<3,"2–3 Years", IF(Table1[[#This Row],[Tenure (Years)]]<5,"3–5 Years", IF(Table1[[#This Row],[Tenure (Years)]]<10,"5–10 Years", "> 10 Years"))))) -> 5–10 Years | R82: =YEAR(Table1[[#This Row],[Hire Date]]) -> 2019 | T82: =IF(Table1[[#This Row],[Education Level]]="Master's Degree", "Master's Degree", IF(Table1[[#This Row],[Education Level]]="Bachelor's Degree", "Bachelor's Degree", "Others")) -> Bachelor's Degree
A83: EMP-10082 | B83: Russell Clark | C83: Male | D83: 38 | E83: Customer Service | F83: East Region | G83: Grade 2 – Junior | H83: Contract | I83: Bachelor's Degree | J83: 45651 | M83: Active | N83: 4135.51 | O83: MGR-10475 | P83: 1.4 | Q83: =IF(Table1[[#This Row],[Tenure (Years)]]<1,"< 1 Year", IF(Table1[[#This Row],[Tenure (Years)]]<2,"1–2 Years", IF(Table1[[#This Row],[Tenure (Years)]]<3,"2–3 Years", IF(Table1[[#This Row],[Tenure (Years)]]<5,"3–5 Years", IF(Table1[[#This Row],[Tenure (Years)]]<10,"5–10 Years", "> 10 Years"))))) -> 1–2 Years | R83: =YEAR(Table1[[#This Row],[Hire Date]]) -> 2024 | T83: =IF(Table1[[#This Row],[Education Level]]="Master's Degree", "Master's Degree", IF(Table1[[#This Row],[Education Level]]="Bachelor's Degree", "Bachelor's Degree", "Others")) -> Bachelor's Degree
A84: EMP-10083 | B84: Peter Fuller | C84: Male | D84: 48 | E84: IT | F84: Head Office | G84: Grade 3 – Mid-Level | H84: Permanent | I84: Bachelor's Degree | J84: 45681 | M84: Active | N84: 8594.75 | O84: MGR-10283 | P84: 1.3 | Q84: =IF(Table1[[#This Row],[Tenure (Years)]]<1,"< 1 Year", IF(Table1[[#This Row],[Tenure (Years)]]<2,"1–2 Years", IF(Table1[[#This Row],[Tenure (Years)]]<3,"2–3 Years", IF(Table1[[#This Row],[Tenure (Years)]]<5,"3–5 Years", IF(Table1[[#This Row],[Tenure (Years)]]<10,"5–10 Years", "> 10 Years"))))) -> 1–2 Years | R84: =YEAR(Table1[[#This Row],[Hire Date]]) -> 2025 | T84: =IF(Table1[[#This Row],[Education Level]]="Master's Degree", "Master's Degree", IF(Table1[[#This Row],[Education Level]]="Bachelor's Degree", "Bachelor's Degree", "Others")) -> Bachelor's Degree
A85: EMP-10084 | B85: Amanda Potter | C85: Female | D85: 30 | E85: Marketing | F85: Head Office | G85: Grade 2 – Junior | H85: Internship | I85: Bachelor's Degree | J85: 44991 | K85: 45220 | L85: End of Contract | M85: Inactive | N85: 6480.64 | O85: MGR-10213 | P85: 0.6 | Q85: =IF(Table1[[#This Row],[Tenure (Years)]]<1,"< 1 Year", IF(Table1[[#This Row],[Tenure (Years)]]<2,"1–2 Years", IF(Table1[[#This Row],[Tenure (Years)]]<3,"2–3 Years", IF(Table1[[#This Row],[Tenure (Years)]]<5,"3–5 Years", IF(Table1[[#This Row],[Tenure (Years)]]<10,"5–10 Years", "> 10 Years"))))) -> < 1 Year | R85: =YEAR(Table1[[#This Row],[Hire Date]]) -> 2023 | S85: =YEAR(Table1[[#This Row],[Exit Date]]) -> 2023 | T85: =IF(Table1[[#This Row],[Education Level]]="Master's Degree", "Master's Degree", IF(Table1[[#This Row],[Education Level]]="Bachelor's Degree", "Bachelor's Degree", "Others")) -> Bachelor's Degree
A86: EMP-10085 | B86: Valerie Thompson | C86: Female | D86: 27 | E86: Risk & Compliance | F86: East Region | G86: Grade 8 – Executive | H86: Permanent | I86: Bachelor's Degree | J86: 44672 | K86: 45363 | L86: Resignation | M86: Inactive | N86: 51093.27 | O86: N/A | P86: 1.9 | Q86: =IF(Table1[[#This Row],[Tenure (Years)]]<1,"< 1 Year", IF(Table1[[#This Row],[Tenure (Years)]]<2,"1–2 Years", IF(Table1[[#This Row],[Tenure (Years)]]<3,"2–3 Years", IF(Table1[[#This Row],[Tenure (Years)]]<5,"3–5 Years", IF(Table1[[#This Row],[Tenure (Years)]]<10,"5–10 Years", "> 10 Years"))))) -> 1–2 Years | R86: =YEAR(Table1[[#This Row],[Hire Date]]) -> 2022 | S86: =YEAR(Table1[[#This Row],[Exit Date]]) -> 2024 | T86: =IF(Table1[[#This Row],[Education Level]]="Master's Degree", "Master's Degree", IF(Table1[[#This Row],[Education Level]]="Bachelor's Degree", "Bachelor's Degree", "Others")) -> Bachelor's Degree
A87: EMP-10086 | B87: Peter Butler | C87: Male | D87: 30 | E87: Marketing | F87: South Region | G87: Grade 3 – Mid-Level | H87: Permanent | I87: Bachelor's Degree | J87: 43111 | M87: Active | N87: 8863.15 | O87: MGR-10251 | P87: 8.3 | Q87: =IF(Table1[[#This Row],[Tenure (Years)]]<1,"< 1 Year", IF(Table1[[#This Row],[Tenure (Years)]]<2,"1–2 Years", IF(Table1[[#This Row],[Tenure (Years)]]<3,"2–3 Years", IF(Table1[[#This Row],[Tenure (Years)]]<5,"3–5 Years", IF(Table1[[#This Row],[Tenure (Years)]]<10,"5–10 Years", "> 10 Years"))))) -> 5–10 Years | R87: =YEAR(Table1[[#This Row],[Hire Date]]) -> 2018 | T87: =IF(Table1[[#This Row],[Education Level]]="Master's Degree", "Master's Degree", IF(Table1[[#This Row],[Education Level]]="Bachelor's Degree", "Bachelor's Degree", "Others")) -> Bachelor's Degree
A88: EMP-10087 | B88: Bryan Dixon | C88: Male | D88: 43 | E88: Operations | F88: West Region | G88: Grade 3 – Mid-Level | H88: Permanent | I88: PhD | J88: 45326 | M88: Active | N88: 7953.02 | O88: MGR-10123 | P88: 2.3 | Q88: =IF(Table1[[#This Row],[Tenure (Years)]]<1,"< 1 Year", IF(Table1[[#This Row],[Tenure (Years)]]<2,"1–2 Years", IF(Table1[[#This Row],[Tenure (Years)]]<3,"2–3 Years", IF(Table1[[#This Row],[Tenure (Years)]]<5,"3–5 Years", IF(Table1[[#This Row],[Tenure (Years)]]<10,"5–10 Years", "> 10 Years"))))) -> 2–3 Years | R88: =YEAR(Table1[[#This Row],[Hire Date]]) -> 2024 | T88: =IF(Table1[[#This Row],[Education Level]]="Master's Degree", "Master's Degree", IF(Table1[[#This Row],[Education Level]]="Bachelor's Degree", "Bachelor's Degree", "Others")) -> Others
A89: EMP-10088 | B89: Matthew Gallagher | C89: Male | D89: 37 | E89: Procurement | F89: West Region | G89: Grade 3 – Mid-Level | H89: Contract | I89: Master's Degree | J89: 44404 | M89: Active | N89: 9068.04 | O89: MGR-10421 | P89: 4.8 | Q89: =IF(Table1[[#This Row],[Tenure (Years)]]<1,"< 1 Year", IF(Table1[[#This Row],[Tenure (Years)]]<2,"1–2 Years", IF(Table1[[#This Row],[Tenure (Years)]]<3,"2–3 Years", IF(Table1[[#This Row],[Tenure (Years)]]<5,"3–5 Years", IF(Table1[[#This Row],[Tenure (Years)]]<10,"5–10 Years", "> 10 Years"))))) -> 3–5 Years | R89: =YEAR(Table1[[#This Row],[Hire Date]]) -> 2021 | T89: =IF(Table1[[#This Row],[Education Level]]="Master's Degree", "Master's Degree", IF(Table1[[#This Row],[Education Level]]="Bachelor's Degree", "Bachelor's Degree", "Others")) -> Master's Degree
A90: EMP-10089 | B90: Fernando Meyer | C90: Male | D90: 30 | E90: Executive Management | F90: Head Office | G90: Grade 8 – Executive | H90: Part-Time | I90: Bachelor's Degree | J90: 45158 | M90: Active | N90: 57383.22 | O90: N/A | P90: 2.7 | Q90: =IF(Table1[[#This Row],[Tenure (Years)]]<1,"< 1 Year", IF(Table1[[#This Row],[Tenure (Years)]]<2,"1–2 Years", IF(Table1[[#This Row],[Tenure (Years)]]<3,"2–3 Years", IF(Table1[[#This Row],[Tenure (Years)]]<5,"3–5 Years", IF(Table1[[#This Row],[Tenure (Years)]]<10,"5–10 Years", "> 10 Years"))))) -> 2–3 Years | R90: =YEAR(Table1[[#This Row],[Hire Date]]) -> 2023 | T90: =IF(Table1[[#This Row],[Education Level]]="Master's Degree", "Master's Degree", IF(Table1[[#This Row],[Education Level]]="Bachelor's Degree", "Bachelor's Degree", "Others")) -> Bachelor's Degree
A91: EMP-10090 | B91: Lisa Bailey | C91: Female | D91: 39 | E91: Human Resources | F91: Head Office | G91: Grade 3 – Mid-Level | H91: Contract | I91: PhD | J91: 44780 | M91: Active | N91: 7870.78 | O91: MGR-10320 | P91: 3.8 | Q91: =IF(Table1[[#This Row],[Tenure (Years)]]<1,"< 1 Year", IF(Table1[[#This Row],[Tenure (Years)]]<2,"1–2 Years", IF(Table1[[#This Row],[Tenure (Years)]]<3,"2–3 Years", IF(Table1[[#This Row],[Tenure (Years)]]<5,"3–5 Years", IF(Table1[[#This Row],[Tenure (Years)]]<10,"5–10 Years", "> 10 Years"))))) -> 3–5 Years | R91: =YEAR(Table1[[#This Row],[Hire Date]]) -> 2022 | T91: =IF(Table1[[#This Row],[Education Level]]="Master's Degree", "Master's Degree", IF(Table1[[#This Row],[Education Level]]="Bachelor's Degree", "Bachelor's Degree", "Others")) -> Others
A92: EMP-10091 | B92: Angela Collins | C92: Female | D92: 35 | E92: Marketing | F92: East Region | G92: Grade 4 – Senior | H92: Permanent | I92: Bachelor's Degree | J92: 45286 | M92: Active | N92: 13332.94 | O92: MGR-10447 | P92: 2.4 | Q92: =IF(Table1[[#This Row],[Tenure (Years)]]<1,"< 1 Year", IF(Table1[[#This Row],[Tenure (Years)]]<2,"1–2 Years", IF(Table1[[#This Row],[Tenure (Years)]]<3,"2–3 Years", IF(Table1[[#This Row],[Tenure (Years)]]<5,"3–5 Years", IF(Table1[[#This Row],[Tenure (Years)]]<10,"5–10 Years", "> 10 Years"))))) -> 2–3 Years | R92: =YEAR(Table1[[#This Row],[Hire Date]]) -> 2023 | T92: =IF(Table1[[#This Row],[Education Level]]="Master's Degree", "Master's Degree", IF(Table1[[#This Row],[Education Level]]="Bachelor's Degree", "Bachelor's Degree", "Others")) -> Bachelor's Degree
A93: EMP-10092 | B93: Brittany Baker | C93: Female | D93: 43 | E93: Customer Service | F93: North Region | G93: Grade 1 – Entry | H93: Part-Time | I93: Master's Degree | J93: 44278 | K93: 45940 | L93: Retirement | M93: Inactive | N93: 2602.63 | O93: MGR-10052 | P93: 4.6 | Q93: =IF(Table1[[#This Row],[Tenure (Years)]]<1,"< 1 Year", IF(Table1[[#This Row],[Tenure (Years)]]<2,"1–2 Years", IF(Table1[[#This Row],[Tenure (Years)]]<3,"2–3 Years", IF(Table1[[#This Row],[Tenure (Years)]]<5,"3–5 Years", IF(Table1[[#This Row],[Tenure (Years)]]<10,"5–10 Years", "> 10 Years"))))) -> 3–5 Years | R93: =YEAR(Table1[[#This Row],[Hire Date]]) -> 2021 | S93: =YEAR(Table1[[#This Row],[Exit Date]]) -> 2025 | T93: =IF(Table1[[#This Row],[Education Level]]="Master's Degree", "Master's Degree", IF(Table1[[#This Row],[Education Level]]="Bachelor's Degree", "Bachelor's Degree", "Others")) -> Master's Degree
A94: EMP-10093 | B94: Benjamin Thompson | C94: Male | D94: 28 | E94: Risk & Compliance | F94: North Region | G94: Grade 3 – Mid-Level | H94: Contract | I94: Bachelor's Degree | J94: 44429 | M94: Active | N94: 7398.4 | O94: MGR-10290 | P94: 4.7 | Q94: =IF(Table1[[#This Row],[Tenure (Years)]]<1,"< 1 Year", IF(Table1[[#This Row],[Tenure (Years)]]<2,"1–2 Years", IF(Table1[[#This Row],[Tenure (Years)]]<3,"2–3 Years", IF(Table1[[#This Row],[Tenure (Years)]]<5,"3–5 Years", IF(Table1[[#This Row],[Tenure (Years)]]<10,"5–10 Years", "> 10 Years"))))) -> 3–5 Years | R94: =YEAR(Table1[[#This Row],[Hire Date]]) -> 2021 | T94: =IF(Table1[[#This Row],[Education Level]]="Master's Degree", "Master's Degree", IF(Table1[[#This Row],[Education Level]]="Bachelor's Degree", "Bachelor's Degree", "Others")) -> Bachelor's Degree
A95: EMP-10094 | B95: Kyle Phillips | C95: Male | D95: 32 | E95: Executive Management | F95: Central Hub | G95: Grade 8 – Executive | H95: Permanent | I95: Bachelor's Degree | J95: 44667 | M95: Active | N95: 49249.59 | O95: N/A | P95: 4.1 | Q95: =IF(Table1[[#This Row],[Tenure (Years)]]<1,"< 1 Year", IF(Table1[[#This Row],[Tenure (Years)]]<2,"1–2 Years", IF(Table1[[#This Row],[Tenure (Years)]]<3,"2–3 Years", IF(Table1[[#This Row],[Tenure (Years)]]<5,"3–5 Years", IF(Table1[[#This Row],[Tenure (Years)]]<10,"5–10 Years", "> 10 Years"))))) -> 3–5 Years | R95: =YEAR(Table1[[#This Row],[Hire Date]]) -> 2022 | T95: =IF(Table1[[#This Row],[Education Level]]="Master's Degree", "Master's Degree", IF(Table1[[#This Row],[Education Level]]="Bachelor's Degree", "Bachelor's Degree", "Others")) -> Bachelor's Degree
A96: EMP-10095 | B96: Angelica Warner | C96: Female | D96: 31 | E96: Risk & Compliance | F96: Head Office | G96: Grade 4 – Senior | H96: Internship | I96: Master's Degree | J96: 45006 | K96: 45249 | L96: End of Contract | M96: Inactive | N96: 11568.07 | O96: MGR-10328 | P96: 0.7 | Q96: =IF(Table1[[#This Row],[Tenure (Years)]]<1,"< 1 Year", IF(Table1[[#This Row],[Tenure (Years)]]<2,"1–2 Years", IF(Table1[[#This Row],[Tenure (Years)]]<3,"2–3 Years", IF(Table1[[#This Row],[Tenure (Years)]]<5,"3–5 Years", IF(Table1[[#This Row],[Tenure (Years)]]<10,"5–10 Years", "> 10 Years"))))) -> < 1 Year | R96: =YEAR(Table1[[#This Row],[Hire Date]]) -> 2023 | S96: =YEAR(Table1[[#This Row],[Exit Date]]) -> 2023 | T96: =IF(Table1[[#This Row],[Education Level]]="Master's Degree", "Master's Degree", IF(Table1[[#This Row],[Education Level]]="Bachelor's Degree", "Bachelor's Degree", "Others")) -> Master's Degree
A97: EMP-10096 | B97: Jeffrey Williams | C97: Male | D97: 22 | E97: Marketing | F97: North Region | G97: Grade 4 – Senior | H97: Contract | I97: Diploma | J97: 44676 | M97: Active | N97: 11555.76 | O97: MGR-10359 | P97: 4.1 | Q97: =IF(Table1[[#This Row],[Tenure (Years)]]<1,"< 1 Year", IF(Table1[[#This Row],[Tenure (Years)]]<2,"1–2 Years", IF(Table1[[#This Row],[Tenure (Years)]]<3,"2–3 Years", IF(Table1[[#This Row],[Tenure (Years)]]<5,"3–5 Years", IF(Table1[[#This Row],[Tenure (Years)]]<10,"5–10 Years", "> 10 Years"))))) -> 3–5 Years | R97: =YEAR(Table1[[#This Row],[Hire Date]]) -> 2022 | T97: =IF(Table1[[#This Row],[Education Level]]="Master's Degree", "Master's Degree", IF(Table1[[#This Row],[Education Level]]="Bachelor's Degree", "Bachelor's Degree", "Others")) -> Others
A98: EMP-10097 | B98: Shane Harrison | C98: Male | D98: 37 | E98: IT | F98: East Region | G98: Grade 1 – Entry | H98: Permanent | I98: Master's Degree | J98: 43134 | K98: 45912 | L98: Retirement | M98: Inactive | N98: 3745.06 | O98: MGR-10427 | P98: 7.6 | Q98: =IF(Table1[[#This Row],[Tenure (Years)]]<1,"< 1 Year", IF(Table1[[#This Row],[Tenure (Years)]]<2,"1–2 Years", IF(Table1[[#This Row],[Tenure (Years)]]<3,"2–3 Years", IF(Table1[[#This Row],[Tenure (Years)]]<5,"3–5 Years", IF(Table1[[#This Row],[Tenure (Years)]]<10,"5–10 Years", "> 10 Years"))))) -> 5–10 Years | R98: =YEAR(Table1[[#This Row],[Hire Date]]) -> 2018 | S98: =YEAR(Table1[[#This Row],[Exit Date]]) -> 2025 | T98: =IF(Table1[[#This Row],[Education Level]]="Master's Degree", "Master's Degree", IF(Table1[[#This Row],[Education Level]]="Bachelor's Degree", "Bachelor's Degree", "Others")) -> Master's Degree
A99: EMP-10098 | B99: Kathy Griffith | C99: Female | D99: 37 | E99: IT | F99: East Region | G99: Grade 5 – Lead | H99: Permanent | I99: Bachelor's Degree | J99: 43998 | M99: Active | N99: 15380.71 | O99: MGR-10338 | P99: 5.9 | Q99: =IF(Table1[[#This Row],[Tenure (Years)]]<1,"< 1 Year", IF(Table1[[#This Row],[Tenure (Years)]]<2,"1–2 Years", IF(Table1[[#This Row],[Tenure (Years)]]<3,"2–3 Years", IF(Table1[[#This Row],[Tenure (Years)]]<5,"3–5 Years", IF(Table1[[#This Row],[Tenure (Years)]]<10,"5–10 Years", "> 10 Years"))))) -> 5–10 Years | R99: =YEAR(Table1[[#This Row],[Hire Date]]) -> 2020 | T99: =IF(Table1[[#This Row],[Education Level]]="Master's Degree", "Master's Degree", IF(Table1[[#This Row],[Education Level]]="Bachelor's Degree", "Bachelor's Degree", "Others")) -> Bachelor's Degree
A100: EMP-10099 | B100: Molly Aguirre | C100: Female | D100: 35 | E100: Executive Management | F100: Head Office | G100: Grade 8 – Executive | H100: Permanent | I100: Master's Degree | J100: 45748 | M100: Active | N100: 60706.2 | O100: N/A | P100: 1.1 | Q100: =IF(Table1[[#This Row],[Tenure (Years)]]<1,"< 1 Year", IF(Table1[[#This Row],[Tenure (Years)]]<2,"1–2 Years", IF(Table1[[#This Row],[Tenure (Years)]]<3,"2–3 Years", IF(Table1[[#This Row],[Tenure (Years)]]<5,"3–5 Years", IF(Table1[[#This Row],[Tenure (Years)]]<10,"5–10 Years", "> 10 Years"))))) -> 1–2 Years | R100: =YEAR(Table1[[#This Row],[Hire Date]]) -> 2025 | T100: =IF(Table1[[#This Row],[Education Level]]="Master's Degree", "Master's Degree", IF(Table1[[#This Row],[Education Level]]="Bachelor's Degree", "Bachelor's Degree", "Others")) -> Master's Degree
...

Sheet CALCULATION SHEET
A1: HEADCOUNT
B4: HEADCOUNT BY DEPT | E4: GENDER DIST | H4: EMPLOYMENT TYPE | K4: EDUCATION LEVEL DIST | N4: HEADCOUNT BY JOBGRADE
B5: Hire Year | C5: (All) | E5: Hire Year | F5: (All) | H5: Hire Year | I5: (All) | K5: Hire Year | L5: (All) | N5: Hire Year | O5: (All)
B6: Status | C6: Active | E6: Status | F6: Active | H6: Status | I6: Active | K6: Status | L6: Active | N6: Status | O6: (All)
B8: Row Labels | C8: Count of Employee ID | E8: Row Labels | F8: Count of Gender | H8: Row Labels | I8: Count of Employment Type | K8: Row Labels | L8: Count of Education Level Cleaned | N8: Row Labels | O8: Count of Employee ID | P8: Count of Employee ID2 | Q8: Average of Monthly Salary ($) | R8: Min. of Monthly Salary ($) | S8: Min. of Monthly Salary ($)2
B9: Risk & Compliance | C9: 379 | E9: Male | F9: 0.5543131 | H9: Internship | I9: 0.024418074 | K9: Bachelor's Degree | L9: 0.50319489 | N9: Grade 1 – Entry | O9: 431 | P9: 0.078363636 | Q9: 3200.497 | R9: 2504.71 | S9: 2504.71
B10: Finance | C10: 383 | E10: Female | F10: 0.4456869 | H10: Part-Time | I10: 0.039707896 | K10: Master's Degree | L10: 0.27453218 | N10: Grade 2 – Junior | O10: 977 | P10: 0.17763636 | Q10: 5297.4411 | R10: 4000.09 | S10: 4000.09
B11: IT | C11: 385 | E11: Grand Total | F11: 1 | H11: Contract | I11: 0.14103149 | K11: Others | L11: 0.22227293 | N11: Grade 3 – Mid-Level | O11: 1336 | P11: 0.24290909 | Q11: 8023.6775 | R11: 6500.74 | S11: 6500.74
B12: Human Resources | C12: 393 | H12: Permanent | I12: 0.79484254 | K12: Grand Total | L12: 1 | N12: Grade 4 – Senior | O12: 1162 | P12: 0.21127273 | Q12: 11740.221 | R12: 9504.89 | S12: 9504.89
B13: Operations | C13: 393 | H13: Grand Total | I13: 1 | N13: Grade 5 – Lead | O13: 622 | P13: 0.11309091 | Q13: 16967.766 | R13: 14004.05 | S13: 14004.05
B14: Legal | C14: 398 | N14: Grade 6 – Manager | O14: 478 | P14: 0.086909091 | Q14: 24897.852 | R14: 20000.78 | S14: 20000.78
B15: Customer Service | C15: 400 | N15: Grade 7 – Director | O15: 314 | P15: 0.057090909 | Q15: 37643.612 | R15: 30019.68 | S15: 30019.68
B16: Sales | C16: 402 | N16: Grade 8 – Executive | O16: 180 | P16: 0.032727273 | Q16: 57750.605 | R16: 45156.31 | S16: 45156.31
B17: Procurement | C17: 407 | N17: Grand Total | O17: 5500 | P17: 1 | Q17: 13743.111 | R17: 2504.71 | S17: 2504.71
B18: Executive Management | C18: 420
B19: Marketing | C19: 422
B20: Grand Total | C20: 4382
B25: HEADCOUNT BY JOB GRADE | E25: HEADCOUNT BY BRANCH | I25: GENDER DIST BY BRANCH | M25: NEW HIRES YTD | P25: ACTIVE HEADCOUNT | S25: GENDER REPRESENTATION
B26: Hire Year | C26: (All) | E26: Hire Year | F26: (All) | I26: Hire Year | J26: (All) | M26: Hire Year | N26: 2026 | P26: Hire Year | Q26: (All) | S26: Hire Year | T26: (All)
B27: Status | C27: Active | E27: Status | F27: Active | I27: Status | J27: Active | P27: Status | Q27: Active | S27: Status | T27: Active
M28: Count of Employee ID
B29: Row Labels | C29: Count of Employee ID | E29: Row Labels | F29: Count of Employee ID | G29: Count of Employee ID2 | I29: Count of Employee ID | J29: Column Labels | M29: 160 | P29: Count of Employee ID | S29: Row Labels | T29: Count of Employee ID
B30: Grade 3 – Mid-Level | C30: 1064 | E30: Central Hub | F30: 486 | G30: 0.11090826 | I30: Row Labels | J30: Male | K30: Female | P30: 4382 | S30: Female | T30: 0.4456869
B31: Grade 4 – Senior | C31: 916 | E31: East Region | F31: 525 | G31: 0.11980831 | I31: Central Hub | J31: 268 | K31: 218 | S31: Male | T31: 0.5543131
B32: Grade 2 – Junior | C32: 796 | E32: Head Office | F32: 1543 | G32: 0.35212232 | I32: East Region | J32: 292 | K32: 233 | S32: Grand Total | T32: 1
B33: Grade 5 – Lead | C33: 499 | E33: North Region | F33: 648 | G33: 0.14787768 | I33: Head Office | J33: 853 | K33: 690
B34: Grade 6 – Manager | C34: 381 | E34: South Region | F34: 661 | G34: 0.15084436 | I34: North Region | J34: 368 | K34: 280
B35: Grade 1 – Entry | C35: 344 | E35: West Region | F35: 519 | G35: 0.11843907 | I35: South Region | J35: 356 | K35: 305
B36: Grade 7 – Director | C36: 249 | E36: Grand Total | F36: 4382 | G36: 1 | I36: West Region | J36: 292 | K36: 227
B37: Grade 8 – Executive | C37: 133 | I37: Grand Total | J37: 2429 | K37: 1953
B38: Grand Total | C38: 4382
B43: HEADCOUNT BY DEPT | F43: HEADCOUNT BY DEPT BY GENDER | K43: HEADCOUNT BY DEPT BY EMP TYPE | P43: HEADCOUNT BY DEPT BY AVG SALARY
B44: Hire Year | C44: (All) | F44: Hire Year | G44: (All) | K44: Hire Year | L44: (All) | P44: Hire Year | Q44: (All)
B45: Status | C45: Active | F45: Status | G45: Active | K45: Status | L45: Active | P45: Status | Q45: Active
B47: Row Labels | C47: Count of Employee ID | D47: Count of Employee ID2 | F47: Count of Employee ID | G47: Column Labels | K47: Count of Employee ID | L47: Column Labels | P47: Row Labels | Q47: Average of Monthly Salary ($)
B48: Risk & Compliance | C48: 379 | D48: 0.086490187 | F48: Row Labels | G48: Male | H48: Female | I48: Grand Total | K48: Row Labels | L48: Permanent | M48: Contract | N48: Grand Total | P48: Human Resources | Q48: 11397.239
B49: Finance | C49: 383 | D49: 0.087403012 | F49: Human Resources | G49: 238 | H49: 155 | I49: 393 | K49: Human Resources | L49: 316 | M49: 53 | N49: 369 | P49: Customer Service | Q49: 7641.1852
B50: IT | C50: 385 | D50: 0.087859425 | F50: Customer Service | G50: 237 | H50: 163 | I50: 400 | K50: Customer Service | L50: 318 | M50: 55 | N50: 373 | P50: Procurement | Q50: 9839.0264
B51: Human Resources | C51: 393 | D51: 0.089685075 | F51: Procurement | G51: 215 | H51: 192 | I51: 407 | K51: Procurement | L51: 319 | M51: 58 | N51: 377 | P51: Risk & Compliance | Q51: 13334.206
B52: Operations | C52: 393 | D52: 0.089685075 | F52: Risk & Compliance | G52: 208 | H52: 171 | I52: 379 | K52: Risk & Compliance | L52: 302 | M52: 53 | N52: 355 | P52: Sales | Q52: 10962.322
B53: Legal | C53: 398 | D53: 0.090826107 | F53: Sales | G53: 203 | H53: 199 | I53: 402 | K53: Sales | L53: 327 | M53: 53 | N53: 380 | P53: Operations | Q53: 8927.6525
B54: Customer Service | C54: 400 | D54: 0.091282519 | F54: Operations | G54: 223 | H54: 170 | I54: 393 | K54: Operations | L54: 321 | M54: 47 | N54: 368 | P54: Finance | Q54: 12996.056
B55: Sales | C55: 402 | D55: 0.091738932 | F55: Finance | G55: 217 | H55: 166 | I55: 383 | K55: Finance | L55: 283 | M55: 67 | N55: 350 | P55: Marketing | Q55: 10248.675
B56: Procurement | C56: 407 | D56: 0.092879963 | F56: Marketing | G56: 220 | H56: 202 | I56: 422 | K56: Marketing | L56: 346 | M56: 55 | N56: 401 | P56: Executive Management | Q56: 36654.423
B57: Executive Management | C57: 420 | D57: 0.095846645 | F57: Executive Management | G57: 230 | H57: 190 | I57: 420 | K57: Executive Management | L57: 327 | M57: 62 | N57: 389 | P57: Legal | Q57: 14416.964
B58: Marketing | C58: 422 | D58: 0.096303058 | F58: Legal | G58: 229 | H58: 169 | I58: 398 | K58: Legal | L58: 316 | M58: 63 | N58: 379 | P58: IT | Q58: 12158.011
B59: Grand Total | C59: 4382 | D59: 1 | F59: IT | G59: 209 | H59: 176 | I59: 385 | K59: IT | L59: 308 | M59: 52 | N59: 360 | P59: Grand Total | Q59: 13606.853
F60: Grand Total | G60: 2429 | H60: 1953 | I60: 4382 | K60: Grand Total | L60: 3483 | M60: 618 | N60: 4101
A72: TURNOVER & ATTRITION
B76: TOTAL EXITS | E76: VOLUNTARY EXIT | H76: INVOLUNTARY EXIT | K76: TENURE AT EXIT
B77: Hire Year | C77: (All) | E77: Hire Year | F77: (All) | H77: Hire Year | I77: (All) | K77: Hire Year | L77: (All)
B78: Exit Year | C78: (Multiple Items) | E78: Exit Year | F78: (Multiple Items) | H78: Exit Year | I78: (Multiple Items) | K78: Exit Year | L78: (Multiple Items)
B79: Status | C79: Inactive | E79: Status | F79: Inactive | H79: Status | I79: Inactive | K79: Status | L79: Inactive
B81: Count of Employee ID | E81: Row Labels | F81: Count of Employee ID | H81: Row Labels | I81: Count of Employee ID | K81: Average of Tenure (Years)
B82: 891 | E82: Health Reasons | F82: 31 | H82: Dismissal | I82: 40 | K82: 2.9833895
E83: Relocation | F83: 34 | H83: End of Contract | I83: 296
E84: Resignation | F84: 327 | H84: Redundancy | I84: 82
E85: Retirement | F85: 81 | H85: Grand Total | I85: 418
E86: Grand Total | F86: 473
I87: =SUM(F86,I85) -> 891
B90: RETENTION RATE | E90: TURNOVER RATE BY DEPT | K90: TURNOVER RATE BY DEPT
E91: Hire Year | F91: (All)
E92: Exit Year | F92: (Multiple Items) | K92: Hire Year | L92: (All) | R92: EXIT REASONS | V92: TENURE AT EXIT
B93: Hire Year | C93: (All) | E93: Status | F93: Inactive | K93: Status | L93: (All) | R93: Hire Year | S93: (All) | V93: Hire Year | W93: (All)
R94: Exit Year | S94: (Multiple Items) | V94: Exit Year | W94: (Multiple Items)
B95: Row Labels | C95: Count of Employee ID | E95: Row Labels | F95: Count of Employee ID | H95: Department | I95: Turnover Rate | K95: Row Labels | L95: Count of Employee ID | R95: Status | S95: Inactive | V95: Status | W95: Inactive
B96: Active | C96: 0.79672727 | E96: Risk & Compliance | F96: 63 | H96: Risk & Compliance | I96: =F96/L96 -> 0.13490364 | K96: Risk & Compliance | L96: 467
B97: Inactive | C97: 0.20327273 | E97: IT | F97: 68 | H97: Information Technology | I97: =F97/L97 -> 0.1399177 | K97: Operations | L97: 486 | R97: Row Labels | S97: Count of Employee ID | V97: Row Labels | W97: Count of Employee ID
B98: Grand Total | C98: 1 | E98: Operations | F98: 69 | H98: Operations | I98: =F98/L98 -> 0.14052953 | K98: Customer Service | L98: 491 | R98: Resignation | S98: 327 | V98: 2–3 Years | W98: 93
E99: Customer Service | F99: 76 | H99: Customer Service | I99: =F99/L99 -> 0.15384615 | K99: Sales | L99: 494 | R99: End of Contract | S99: 296 | V99: 3–5 Years | W99: 174
E100: Sales | F100: 76 | H100: Sales | I100: =F100/L100 -> 0.15447154 | K100: Legal | L100: 492 | R100: Redundancy | S100: 82 | V100: 1–2 Years | W100: 189
E101: Finance | F101: 77 | H101: Legal | I101: =F101/L101 -> 0.15942029 | K101: Finance | L101: 483 | R101: Retirement | S101: 81 | V101: 5–10 Years | W101: 217
E102: Legal | F102: 78 | H102: Finance | I102: =F102/L102 -> 0.15384615 | K102: Procurement | L102: 507 | R102: Dismissal | S102: 40 | V102: < 1 Year | W102: 218
E103: Procurement | F103: 82 | H103: Procurement | I103: =F103/L103 -> 0.15101289 | K103: Marketing | L103: 543 | R103: Relocation | S103: 34 | V103: Grand Total | W103: 891
E104: Marketing | F104: 95 | H104: Marketing | I104: =F104/L104 -> 0.18375242 | K104: Human Resources | L104: 517 | R104: Health Reasons | S104: 31
E105: Human Resources | F105: 96 | H105: Human Resources | I105: =F105/L105 -> 0.17582418 | K105: Executive Management | L105: 546 | R105: Grand Total | S105: 891
E106: Executive Management | F106: 111 | H106: Executive Management | I106: =F106/L106 -> 0.23417722 | K106: IT | L106: 474
E107: Grand Total | F107: 891 | K107: Grand Total | L107: 5500
A113: TRAINING
F116: TOTAL ENROLMENT | I116: COMPLETION RATE | L116: TOTAL COST | O116: AVG. ROI | R116: AVG. SCORE IMPROVEMENT BY PROG
B117: Training Date | C117: (All) | F117: Training Date | G117: (All) | I117: Training Date | J117: (All) | L117: Training Date | M117: (All) | O117: Training Date | P117: (All) | R117: Training Date | S117: (All)
O118: Score Improvement(%) | P118: (Multiple Items) | R118: Score Improvement(%) | S118: (Multiple Items)
B119: Row Labels | C119: Count of Program Name | F119: Count of Employee ID | I119: Row Labels | J119: Count of Employee ID | L119: Sum of Cost per Head ($)
B120: Compliance & Ethics | C120: 200 | F120: 2172 | I120: No | J120: 0.07320442 | L120: 2589100 | O120: Average of Score Improvement(%) | R120: Row Labels | S120: Average of Score Improvement(%)
B121: Customer Experience Excellence | C121: 236 | I121: Yes | J121: 0.92679558 | O121: 0.34835102 | R121: Performance Management Coaching | S121: 0.39398209
B122: Cybersecurity Awareness | C122: 152 | I122: Grand Total | J122: 1 | L122: =L120/1000000 -> 2.5891 | R122: Financial Acumen for Non-Finance | S122: 0.38085973
B123: Diversity & Inclusion | C123: 113 | R123: Leadership Development | S123: 0.3780557
B124: Excel & Data Analytics | C124: 129 | R124: Project Management (PMP Prep) | S124: 0.37125076
B125: Financial Acumen for Non-Finance | C125: 221 | R125: Compliance & Ethics | S125: 0.36662907
B126: Health & Safety | C126: 244 | R126: Diversity & Inclusion | S126: 0.35525039
B127: Leadership Development | C127: 109 | R127: Customer Experience Excellence | S127: 0.35519733
B128: Onboarding Programme | C128: 216 | R128: Health & Safety | S128: 0.35148601
B129: Performance Management Coaching | C129: 112 | R129: Onboarding Programme | S129: 0.34728294
B130: Project Management (PMP Prep) | C130: 302 | R130: Cybersecurity Awareness | S130: 0.30960637
B131: Sales Techniques & Negotiation | C131: 138 | R131: Sales Techniques & Negotiation | S131: 0.26556517
B132: Grand Total | C132: 2172 | R132: Excel & Data Analytics | S132: 0.25786789
R133: Grand Total | S133: 0.34835102
B134: COUNT OF PROGRAMMES | C134: =COUNTA(B120:B131) -> 12

Sheet DASHBOARD OVERVIEW
A6: DASHBOARD
B8: Overview
B10: Headcount
B12: Attrition
B14: Training & ROI
A20: Period: Jan 2024 – May 2026

Sheet HEADCOUNT ANALYSIS
D1: HEADCOUNT ANALYSIS
A6: DASHBOARD
B8: Overview
B10: Headcount
B12: Attrition
B14: Training & ROI
E19: DEPARTMENT | H19: HEADCOUNT | J19: % OF TOTAL | L19: MALE | M19: FEMALE | N19: PERMANENT | P19: CONTRACT | R19: AVG. SALARY | T19: DISTRIBUTION
A20: Period: Jan 2024 – May 2026
E21: Human Resources | H21: ='CALCULATION SHEET'!C48 -> 379 | J21: ='CALCULATION SHEET'!D48 -> 0.086490187 | L21: ='CALCULATION SHEET'!G49 -> 238 | M21: ='CALCULATION SHEET'!H49 -> 155 | N21: ='CALCULATION SHEET'!L49 -> 316 | P21: ='CALCULATION SHEET'!M49 -> 53 | R21: ='CALCULATION SHEET'!Q48 -> 11397.239 | T21: =H21 -> 379
E22: Customer Service | H22: ='CALCULATION SHEET'!C49 -> 383 | J22: ='CALCULATION SHEET'!D49 -> 0.087403012 | L22: ='CALCULATION SHEET'!G50 -> 237 | M22: ='CALCULATION SHEET'!H50 -> 163 | N22: ='CALCULATION SHEET'!L50 -> 318 | P22: ='CALCULATION SHEET'!M50 -> 55 | R22: ='CALCULATION SHEET'!Q49 -> 7641.1852 | T22: =H22 -> 383
E23: Procurement | H23: ='CALCULATION SHEET'!C50 -> 385 | J23: ='CALCULATION SHEET'!D50 -> 0.087859425 | L23: ='CALCULATION SHEET'!G51 -> 215 | M23: ='CALCULATION SHEET'!H51 -> 192 | N23: ='CALCULATION SHEET'!L51 -> 319 | P23: ='CALCULATION SHEET'!M51 -> 58 | R23: ='CALCULATION SHEET'!Q50 -> 9839.0264 | T23: =H23 -> 385
E24: Risk & Compliance | H24: ='CALCULATION SHEET'!C51 -> 393 | J24: ='CALCULATION SHEET'!D51 -> 0.089685075 | L24: ='CALCULATION SHEET'!G52 -> 208 | M24: ='CALCULATION SHEET'!H52 -> 171 | N24: ='CALCULATION SHEET'!L52 -> 302 | P24: ='CALCULATION SHEET'!M52 -> 53 | R24: ='CALCULATION SHEET'!Q51 -> 13334.206 | T24: =H24 -> 393
E25: Sales | H25: ='CALCULATION SHEET'!C52 -> 393 | J25: ='CALCULATION SHEET'!D52 -> 0.089685075 | L25: ='CALCULATION SHEET'!G53 -> 203 | M25: ='CALCULATION SHEET'!H53 -> 199 | N25: ='CALCULATION SHEET'!L53 -> 327 | P25: ='CALCULATION SHEET'!M53 -> 53 | R25: ='CALCULATION SHEET'!Q52 -> 10962.322 | T25: =H25 -> 393
E26: Operations | H26: ='CALCULATION SHEET'!C53 -> 398 | J26: ='CALCULATION SHEET'!D53 -> 0.090826107 | L26: ='CALCULATION SHEET'!G54 -> 223 | M26: ='CALCULATION SHEET'!H54 -> 170 | N26: ='CALCULATION SHEET'!L54 -> 321 | P26: ='CALCULATION SHEET'!M54 -> 47 | R26: ='CALCULATION SHEET'!Q53 -> 8927.6525 | T26: =H26 -> 398
E27: Information Technology | H27: ='CALCULATION SHEET'!C54 -> 400 | J27: ='CALCULATION SHEET'!D54 -> 0.091282519 | L27: ='CALCULATION SHEET'!G55 -> 217 | M27: ='CALCULATION SHEET'!H55 -> 166 | N27: ='CALCULATION SHEET'!L55 -> 283 | P27: ='CALCULATION SHEET'!M55 -> 67 | R27: ='CALCULATION SHEET'!Q54 -> 12996.056 | T27: =H27 -> 400
E28: Finance | H28: ='CALCULATION SHEET'!C55 -> 402 | J28: ='CALCULATION SHEET'!D55 -> 0.091738932 | L28: ='CALCULATION SHEET'!G56 -> 220 | M28: ='CALCULATION SHEET'!H56 -> 202 | N28: ='CALCULATION SHEET'!L56 -> 346 | P28: ='CALCULATION SHEET'!M56 -> 55 | R28: ='CALCULATION SHEET'!Q55 -> 10248.675 | T28: =H28 -> 402
E29: Marketing | H29: ='CALCULATION SHEET'!C56 -> 407 | J29: ='CALCULATION SHEET'!D56 -> 0.092879963 | L29: ='CALCULATION SHEET'!G57 -> 230 | M29: ='CALCULATION SHEET'!H57 -> 190 | N29: ='CALCULATION SHEET'!L57 -> 327 | P29: ='CALCULATION SHEET'!M57 -> 62 | R29: ='CALCULATION SHEET'!Q56 -> 36654.423 | T29: =H29 -> 407
E30: Executive Management | H30: ='CALCULATION SHEET'!C57 -> 420 | J30: ='CALCULATION SHEET'!D57 -> 0.095846645 | L30: ='CALCULATION SHEET'!G58 -> 229 | M30: ='CALCULATION SHEET'!H58 -> 169 | N30: ='CALCULATION SHEET'!L58 -> 316 | P30: ='CALCULATION SHEET'!M58 -> 63 | R30: ='CALCULATION SHEET'!Q57 -> 14416.964 | T30: =H30 -> 420
E31: Legal | H31: ='CALCULATION SHEET'!C58 -> 422 | J31: ='CALCULATION SHEET'!D58 -> 0.096303058 | L31: ='CALCULATION SHEET'!G59 -> 209 | M31: ='CALCULATION SHEET'!H59 -> 176 | N31: ='CALCULATION SHEET'!L59 -> 308 | P31: ='CALCULATION SHEET'!M59 -> 52 | R31: ='CALCULATION SHEET'!Q58 -> 12158.011 | T31: =H31 -> 422

Sheet ATTRITION
D1: ATTRITION ANALYSIS
A6: DASHBOARD
B8: Overview
B10: Headcount
B12: Attrition
B14: Training & ROI
A20: Period: Jan 2024 – May 2026

Sheet TRAINING
D1: TRAINING ANALYSIS
A6: DASHBOARD
B8: Overview
B10: Headcount
B12: Attrition
B14: Training & ROI
A20: Period: Jan 2024 – May 2026

Sheet TRAINING DATA 
A1: Training ID | B1: Program Name | C1: Category | D1: Training Date | E1: Duration (Days) | F1: Employee ID | G1: Department | H1: Job Grade | I1: Cost per Head ($) | J1: Completed | K1: Pre-Training Score | L1: Post-Training Score | M1: Score Improvement | N1: Score Improvement(%)
A2: TRN-3001 | B2: Leadership Development | C2: Leadership | D2: 45651 | E2: 3 | F2: EMP-14282 | G2: Procurement | H2: Grade 3 – Mid-Level | I2: 3500 | J2: Yes | K2: 50.5 | L2: 73.2 | M2: =Table2[[#This Row],[Post-Training Score]]-Table2[[#This Row],[Pre-Training Score]] -> 22.7 | N2: =(Table2[[#This Row],[Score Improvement]]/Table2[[#This Row],[Pre-Training Score]]) -> 0.44950495
A3: TRN-3001 | B3: Leadership Development | C3: Leadership | D3: 45651 | E3: 3 | F3: EMP-14957 | G3: Information Technology | H3: Grade 3 – Mid-Level | I3: 3500 | J3: Yes | K3: 42.3 | L3: 53.8 | M3: =Table2[[#This Row],[Post-Training Score]]-Table2[[#This Row],[Pre-Training Score]] -> 11.5 | N3: =(Table2[[#This Row],[Score Improvement]]/Table2[[#This Row],[Pre-Training Score]]) -> 0.27186761
A4: TRN-3001 | B4: Leadership Development | C4: Leadership | D4: 45651 | E4: 3 | F4: EMP-10101 | G4: Information Technology | H4: Grade 5 – Lead | I4: 3500 | J4: Yes | K4: 66.5 | L4: 85.3 | M4: =Table2[[#This Row],[Post-Training Score]]-Table2[[#This Row],[Pre-Training Score]] -> 18.8 | N4: =(Table2[[#This Row],[Score Improvement]]/Table2[[#This Row],[Pre-Training Score]]) -> 0.28270677
A5: TRN-3001 | B5: Leadership Development | C5: Leadership | D5: 45651 | E5: 3 | F5: EMP-13494 | G5: Procurement | H5: Grade 2 – Junior | I5: 3500 | J5: Yes | K5: 51.8 | L5: 65.2 | M5: =Table2[[#This Row],[Post-Training Score]]-Table2[[#This Row],[Pre-Training Score]] -> 13.4 | N5: =(Table2[[#This Row],[Score Improvement]]/Table2[[#This Row],[Pre-Training Score]]) -> 0.25868726
A6: TRN-3001 | B6: Leadership Development | C6: Leadership | D6: 45651 | E6: 3 | F6: EMP-11989 | G6: Executive Management | H6: Grade 7 – Director | I6: 3500 | J6: Yes | K6: 49.2 | L6: 62.3 | M6: =Table2[[#This Row],[Post-Training Score]]-Table2[[#This Row],[Pre-Training Score]] -> 13.1 | N6: =(Table2[[#This Row],[Score Improvement]]/Table2[[#This Row],[Pre-Training Score]]) -> 0.26626016
A7: TRN-3001 | B7: Leadership Development | C7: Leadership | D7: 45651 | E7: 3 | F7: EMP-12564 | G7: Customer Service | H7: Grade 3 – Mid-Level | I7: 3500 | J7: Yes | K7: 58.9 | L7: 86.4 | M7: =Table2[[#This Row],[Post-Training Score]]-Table2[[#This Row],[Pre-Training Score]] -> 27.5 | N7: =(Table2[[#This Row],[Score Improvement]]/Table2[[#This Row],[Pre-Training Score]]) -> 0.46689304
A8: TRN-3001 | B8: Leadership Development | C8: Leadership | D8: 45651 | E8: 3 | F8: EMP-10424 | G8: Human Resources | H8: Grade 4 – Senior | I8: 3500 | J8: Yes | K8: 40.8 | L8: 71.6 | M8: =Table2[[#This Row],[Post-Training Score]]-Table2[[#This Row],[Pre-Training Score]] -> 30.8 | N8: =(Table2[[#This Row],[Score Improvement]]/Table2[[#This Row],[Pre-Training Score]]) -> 0.75490196
A9: TRN-3001 | B9: Leadership Development | C9: Leadership | D9: 45651 | E9: 3 | F9: EMP-15477 | G9: Procurement | H9: Grade 1 – Entry | I9: 3500 | J9: No | M9: =Table2[[#This Row],[Post-Training Score]]-Table2[[#This Row],[Pre-Training Score]] -> 0 | N9: =(Table2[[#This Row],[Score Improvement]]/Table2[[#This Row],[Pre-Training Score]]) -> #DIV/0!
A10: TRN-3001 | B10: Leadership Development | C10: Leadership | D10: 45651 | E10: 3 | F10: EMP-13374 | G10: Risk & Compliance | H10: Grade 1 – Entry | I10: 3500 | J10: Yes | K10: 60.7 | L10: 83.7 | M10: =Table2[[#This Row],[Post-Training Score]]-Table2[[#This Row],[Pre-Training Score]] -> 23 | N10: =(Table2[[#This Row],[Score Improvement]]/Table2[[#This Row],[Pre-Training Score]]) -> 0.37891269
A11: TRN-3001 | B11: Leadership Development | C11: Leadership | D11: 45651 | E11: 3 | F11: EMP-10910 | G11: Customer Service | H11: Grade 4 – Senior | I11: 3500 | J11: Yes | K11: 42.6 | L11: 55.9 | M11: =Table2[[#This Row],[Post-Training Score]]-Table2[[#This Row],[Pre-Training Score]] -> 13.3 | N11: =(Table2[[#This Row],[Score Improvement]]/Table2[[#This Row],[Pre-Training Score]]) -> 0.31220657
A12: TRN-3001 | B12: Leadership Development | C12: Leadership | D12: 45651 | E12: 3 | F12: EMP-12047 | G12: Risk & Compliance | H12: Grade 2 – Junior | I12: 3500 | J12: Yes | K12: 63.8 | L12: 88 | M12: =Table2[[#This Row],[Post-Training Score]]-Table2[[#This Row],[Pre-Training Score]] -> 24.2 | N12: =(Table2[[#This Row],[Score Improvement]]/Table2[[#This Row],[Pre-Training Score]]) -> 0.37931034
A13: TRN-3001 | B13: Leadership Development | C13: Leadership | D13: 45651 | E13: 3 | F13: EMP-13954 | G13: Human Resources | H13: Grade 4 – Senior | I13: 3500 | J13: Yes | K13: 50.3 | L13: 77.3 | M13: =Table2[[#This Row],[Post-Training Score]]-Table2[[#This Row],[Pre-Training Score]] -> 27 | N13: =(Table2[[#This Row],[Score Improvement]]/Table2[[#This Row],[Pre-Training Score]]) -> 0.53677932
A14: TRN-3001 | B14: Leadership Development | C14: Leadership | D14: 45651 | E14: 3 | F14: EMP-10613 | G14: Human Resources | H14: Grade 3 – Mid-Level | I14: 3500 | J14: Yes | K14: 48 | L14: 59.4 | M14: =Table2[[#This Row],[Post-Training Score]]-Table2[[#This Row],[Pre-Training Score]] -> 11.4 | N14: =(Table2[[#This Row],[Score Improvement]]/Table2[[#This Row],[Pre-Training Score]]) -> 0.2375
A15: TRN-3001 | B15: Leadership Development | C15: Leadership | D15: 45651 | E15: 3 | F15: EMP-14087 | G15: Sales | H15: Grade 2 – Junior | I15: 3500 | J15: Yes | K15: 44.8 | L15: 77.3 | M15: =Table2[[#This Row],[Post-Training Score]]-Table2[[#This Row],[Pre-Training Score]] -> 32.5 | N15: =(Table2[[#This Row],[Score Improvement]]/Table2[[#This Row],[Pre-Training Score]]) -> 0.72544643
A16: TRN-3001 | B16: Leadership Development | C16: Leadership | D16: 45651 | E16: 3 | F16: EMP-14138 | G16: Information Technology | H16: Grade 4 – Senior | I16: 3500 | J16: Yes | K16: 69.1 | L16: 92.6 | M16: =Table2[[#This Row],[Post-Training Score]]-Table2[[#This Row],[Pre-Training Score]] -> 23.5 | N16: =(Table2[[#This Row],[Score Improvement]]/Table2[[#This Row],[Pre-Training Score]]) -> 0.34008683
A17: TRN-3001 | B17: Leadership Development | C17: Leadership | D17: 45651 | E17: 3 | F17: EMP-11877 | G17: Legal | H17: Grade 6 – Manager | I17: 3500 | J17: Yes | K17: 70.8 | L17: 100 | M17: =Table2[[#This Row],[Post-Training Score]]-Table2[[#This Row],[Pre-Training Score]] -> 29.2 | N17: =(Table2[[#This Row],[Score Improvement]]/Table2[[#This Row],[Pre-Training Score]]) -> 0.41242938
A18: TRN-3001 | B18: Leadership Development | C18: Leadership | D18: 45651 | E18: 3 | F18: EMP-13167 | G18: Marketing | H18: Grade 3 – Mid-Level | I18: 3500 | J18: Yes | K18: 66.4 | L18: 77.4 | M18: =Table2[[#This Row],[Post-Training Score]]-Table2[[#This Row],[Pre-Training Score]] -> 11 | N18: =(Table2[[#This Row],[Score Improvement]]/Table2[[#This Row],[Pre-Training Score]]) -> 0.16566265
A19: TRN-3001 | B19: Leadership Development | C19: Leadership | D19: 45651 | E19: 3 | F19: EMP-13736 | G19: Information Technology | H19: Grade 2 – Junior | I19: 3500 | J19: Yes | K19: 69.2 | L19: 86.1 | M19: =Table2[[#This Row],[Post-Training Score]]-Table2[[#This Row],[Pre-Training Score]] -> 16.9 | N19: =(Table2[[#This Row],[Score Improvement]]/Table2[[#This Row],[Pre-Training Score]]) -> 0.24421965
A20: TRN-3001 | B20: Leadership Development | C20: Leadership | D20: 45651 | E20: 3 | F20: EMP-14272 | G20: Risk & Compliance | H20: Grade 6 – Manager | I20: 3500 | J20: Yes | K20: 53.8 | L20: 81.7 | M20: =Table2[[#This Row],[Post-Training Score]]-Table2[[#This Row],[Pre-Training Score]] -> 27.9 | N20: =(Table2[[#This Row],[Score Improvement]]/Table2[[#This Row],[Pre-Training Score]]) -> 0.51858736
A21: TRN-3001 | B21: Leadership Development | C21: Leadership | D21: 45651 | E21: 3 | F21: EMP-10909 | G21: Information Technology | H21: Grade 3 – Mid-Level | I21: 3500 | J21: Yes | K21: 41.4 | L21: 68.3 | M21: =Table2[[#This Row],[Post-Training Score]]-Table2[[#This Row],[Pre-Training Score]] -> 26.9 | N21: =(Table2[[#This Row],[Score Improvement]]/Table2[[#This Row],[Pre-Training Score]]) -> 0.64975845
... A40: TRN-3001 | B40: Leadership Development | C40: Leadership | D40: 45651 | E40: 3 | F40: EMP-14167 | G40: Marketing | H40: Grade 1 – Entry | I40: 3500 | J40: Yes | K40: 68.3 | L40: 96.4 | M40: =Table2[[#This Row],[Post-Training Score]]-Table2[[#This Row],[Pre-Training Score]] -> 28.1 | N40: =(Table2[[#This Row],[Score Improvement]]/Table2[[#This Row],[Pre-Training Score]]) -> 0.4114202
A41: TRN-3001 | B41: Leadership Development | C41: Leadership | D41: 45651 | E41: 3 | F41: EMP-12073 | G41: Human Resources | H41: Grade 3 – Mid-Level | I41: 3500 | J41: No | M41: =Table2[[#This Row],[Post-Training Score]]-Table2[[#This Row],[Pre-Training Score]] -> 0 | N41: =(Table2[[#This Row],[Score Improvement]]/Table2[[#This Row],[Pre-Training Score]]) -> #DIV/0!
A42: TRN-3001 | B42: Leadership Development | C42: Leadership | D42: 45651 | E42: 3 | F42: EMP-10041 | G42: Human Resources | H42: Grade 6 – Manager | I42: 3500 | J42: No | M42: =Table2[[#This Row],[Post-Training Score]]-Table2[[#This Row],[Pre-Training Score]] -> 0 | N42: =(Table2[[#This Row],[Score Improvement]]/Table2[[#This Row],[Pre-Training Score]]) -> #DIV/0!
A43: TRN-3001 | B43: Leadership Development | C43: Leadership | D43: 45651 | E43: 3 | F43: EMP-14089 | G43: Legal | H43: Grade 3 – Mid-Level | I43: 3500 | J43: Yes | K43: 52.7 | L43: 77.2 | M43: =Table2[[#This Row],[Post-Training Score]]-Table2[[#This Row],[Pre-Training Score]] -> 24.5 | N43: =(Table2[[#This Row],[Score Improvement]]/Table2[[#This Row],[Pre-Training Score]]) -> 0.46489564
A44: TRN-3001 | B44: Leadership Development | C44: Leadership | D44: 45651 | E44: 3 | F44: EMP-12071 | G44: Sales | H44: Grade 3 – Mid-Level | I44: 3500 | J44: Yes | K44: 47.2 | L44: 63.9 | M44: =Table2[[#This Row],[Post-Training Score]]-Table2[[#This Row],[Pre-Training Score]] -> 16.7 | N44: =(Table2[[#This Row],[Score Improvement]]/Table2[[#This Row],[Pre-Training Score]]) -> 0.35381356
A45: TRN-3001 | B45: Leadership Development | C45: Leadership | D45: 45651 | E45: 3 | F45: EMP-13371 | G45: Human Resources | H45: Grade 3 – Mid-Level | I45: 3500 | J45: Yes | K45: 73.5 | L45: 79 | M45: =Table2[[#This Row],[Post-Training Score]]-Table2[[#This Row],[Pre-Training Score]] -> 5.5 | N45: =(Table2[[#This Row],[Score Improvement]]/Table2[[#This Row],[Pre-Training Score]]) -> 0.074829932
A46: TRN-3001 | B46: Leadership Development | C46: Leadership | D46: 45651 | E46: 3 | F46: EMP-12929 | G46: Procurement | H46: Grade 1 – Entry | I46: 3500 | J46: Yes | K46: 42.8 | L46: 55.1 | M46: =Table2[[#This Row],[Post-Training Score]]-Table2[[#This Row],[Pre-Training Score]] -> 12.3 | N46: =(Table2[[#This Row],[Score Improvement]]/Table2[[#This Row],[Pre-Training Score]]) -> 0.28738318
A47: TRN-3001 | B47: Leadership Development | C47: Leadership | D47: 45651 | E47: 3 | F47: EMP-15407 | G47: Customer Service | H47: Grade 1 – Entry | I47: 3500 | J47: Yes | K47: 42.4 | L47: 53.1 | M47: =Table2[[#This Row],[Post-Training Score]]-Table2[[#This Row],[Pre-Training Score]] -> 10.7 | N47: =(Table2[[#This Row],[Score Improvement]]/Table2[[#This Row],[Pre-Training Score]]) -> 0.25235849
A48: TRN-3001 | B48: Leadership Development | C48: Leadership | D48: 45651 | E48: 3 | F48: EMP-13583 | G48: Finance | H48: Grade 4 – Senior | I48: 3500 | J48: Yes | K48: 54 | L48: 63.8 | M48: =Table2[[#This Row],[Post-Training Score]]-Table2[[#This Row],[Pre-Training Score]] -> 9.8 | N48: =(Table2[[#This Row],[Score Improvement]]/Table2[[#This Row],[Pre-Training Score]]) -> 0.18148148
A49: TRN-3001 | B49: Leadership Development | C49: Leadership | D49: 45651 | E49: 3 | F49: EMP-11994 | G49: Executive Management | H49: Grade 7 – Director | I49: 3500 | J49: Yes | K49: 55.4 | L49: 90.3 | M49: =Table2[[#This Row],[Post-Training Score]]-Table2[[#This Row],[Pre-Training Score]] -> 34.9 | N49: =(Table2[[#This Row],[Score Improvement]]/Table2[[#This Row],[Pre-Training Score]]) -> 0.6299639
A50: TRN-3001 | B50: Leadership Development | C50: Leadership | D50: 45651 | E50: 3 | F50: EMP-14296 | G50: Procurement | H50: Grade 3 – Mid-Level | I50: 3500 | J50: Yes | K50: 43 | L50: 65.8 | M50: =Table2[[#This Row],[Post-Training Score]]-Table2[[#This Row],[Pre-Training Score]] -> 22.8 | N50: =(Table2[[#This Row],[Score Improvement]]/Table2[[#This Row],[Pre-Training Score]]) -> 0.53023256
A51: TRN-3001 | B51: Leadership Development | C51: Leadership | D51: 45651 | E51: 3 | F51: EMP-10924 | G51: Risk & Compliance | H51: Grade 6 – Manager | I51: 3500 | J51: Yes | K51: 52 | L51: 63.2 | M51: =Table2[[#This Row],[Post-Training Score]]-Table2[[#This Row],[Pre-Training Score]] -> 11.2 | N51: =(Table2[[#This Row],[Score Improvement]]/Table2[[#This Row],[Pre-Training Score]]) -> 0.21538462
A52: TRN-3001 | B52: Leadership Development | C52: Leadership | D52: 45651 | E52: 3 | F52: EMP-10142 | G52: Customer Service | H52: Grade 1 – Entry | I52: 3500 | J52: Yes | K52: 73.9 | L52: 80.2 | M52: =Table2[[#This Row],[Post-Training Score]]-Table2[[#This Row],[Pre-Training Score]] -> 6.3 | N52: =(Table2[[#This Row],[Score Improvement]]/Table2[[#This Row],[Pre-Training Score]]) -> 0.085250338
A53: TRN-3001 | B53: Leadership Development | C53: Leadership | D53: 45651 | E53: 3 | F53: EMP-12995 | G53: Executive Management | H53: Grade 5 – Lead | I53: 3500 | J53: Yes | K53: 65.2 | L53: 80.5 | M53: =Table2[[#This Row],[Post-Training Score]]-Table2[[#This Row],[Pre-Training Score]] -> 15.3 | N53: =(Table2[[#This Row],[Score Improvement]]/Table2[[#This Row],[Pre-Training Score]]) -> 0.23466258
A54: TRN-3001 | B54: Leadership Development | C54: Leadership | D54: 45651 | E54: 3 | F54: EMP-15290 | G54: Sales | H54: Grade 1 – Entry | I54: 3500 | J54: Yes | K54: 40.3 | L54: 49.4 | M54: =Table2[[#This Row],[Post-Training Score]]-Table2[[#This Row],[Pre-Training Score]] -> 9.1 | N54: =(Table2[[#This Row],[Score Improvement]]/Table2[[#This Row],[Pre-Training Score]]) -> 0.22580645
... A61: TRN-3001 | B61: Leadership Development | C61: Leadership | D61: 45651 | E61: 3 | F61: EMP-14970 | G61: Human Resources | H61: Grade 2 – Junior | I61: 3500 | J61: Yes | K61: 63.8 | L61: 76.7 | M61: =Table2[[#This Row],[Post-Training Score]]-Table2[[#This Row],[Pre-Training Score]] -> 12.9 | N61: =(Table2[[#This Row],[Score Improvement]]/Table2[[#This Row],[Pre-Training Score]]) -> 0.20219436
A62: TRN-3001 | B62: Leadership Development | C62: Leadership | D62: 45651 | E62: 3 | F62: EMP-13688 | G62: Finance | H62: Grade 4 – Senior | I62: 3500 | J62: No | M62: =Table2[[#This Row],[Post-Training Score]]-Table2[[#This Row],[Pre-Training Score]] -> 0 | N62: =(Table2[[#This Row],[Score Improvement]]/Table2[[#This Row],[Pre-Training Score]]) -> #DIV/0!
A63: TRN-3001 | B63: Leadership Development | C63: Leadership | D63: 45651 | E63: 3 | F63: EMP-15447 | G63: Procurement | H63: Grade 3 – Mid-Level | I63: 3500 | J63: Yes | K63: 54 | L63: 62.9 | M63: =Table2[[#This Row],[Post-Training Score]]-Table2[[#This Row],[Pre-Training Score]] -> 8.9 | N63: =(Table2[[#This Row],[Score Improvement]]/Table2[[#This Row],[Pre-Training Score]]) -> 0.16481481
A64: TRN-3001 | B64: Leadership Development | C64: Leadership | D64: 45651 | E64: 3 | F64: EMP-12611 | G64: Marketing | H64: Grade 2 – Junior | I64: 3500 | J64: Yes | K64: 74.7 | L64: 100 | M64: =Table2[[#This Row],[Post-Training Score]]-Table2[[#This Row],[Pre-Training Score]] -> 25.3 | N64: =(Table2[[#This Row],[Score Improvement]]/Table2[[#This Row],[Pre-Training Score]]) -> 0.33868809
A65: TRN-3001 | B65: Leadership Development | C65: Leadership | D65: 45651 | E65: 3 | F65: EMP-10572 | G65: Information Technology | H65: Grade 5 – Lead | I65: 3500 | J65: No | M65: =Table2[[#This Row],[Post-Training Score]]-Table2[[#This Row],[Pre-Training Score]] -> 0 | N65: =(Table2[[#This Row],[Score Improvement]]/Table2[[#This Row],[Pre-Training Score]]) -> #DIV/0!
A66: TRN-3001 | B66: Leadership Development | C66: Leadership | D66: 45651 | E66: 3 | F66: EMP-11743 | G66: Customer Service | H66: Grade 1 – Entry | I66: 3500 | J66: Yes | K66: 67.8 | L66: 81.5 | M66: =Table2[[#This Row],[Post-Training Score]]-Table2[[#This Row],[Pre-Training Score]] -> 13.7 | N66: =(Table2[[#This Row],[Score Improvement]]/Table2[[#This Row],[Pre-Training Score]]) -> 0.2020649
A67: TRN-3002 | B67: Leadership Development | C67: Leadership | D67: 45567 | E67: 3 | F67: EMP-15216 | G67: Legal | H67: Grade 3 – Mid-Level | I67: 3500 | J67: Yes | K67: 55.8 | L67: 83.7 | M67: =Table2[[#This Row],[Post-Training Score]]-Table2[[#This Row],[Pre-Training Score]] -> 27.9 | N67: =(Table2[[#This Row],[Score Improvement]]/Table2[[#This Row],[Pre-Training Score]]) -> 0.5
A68: TRN-3002 | B68: Leadership Development | C68: Leadership | D68: 45567 | E68: 3 | F68: EMP-13509 | G68: Information Technology | H68: Grade 2 – Junior | I68: 3500 | J68: Yes | K68: 40.3 | L68: 46.2 | M68: =Table2[[#This Row],[Post-Training Score]]-Table2[[#This Row],[Pre-Training Score]] -> 5.9 | N68: =(Table2[[#This Row],[Score Improvement]]/Table2[[#This Row],[Pre-Training Score]]) -> 0.14640199
A69: TRN-3002 | B69: Leadership Development | C69: Leadership | D69: 45567 | E69: 3 | F69: EMP-10178 | G69: Procurement | H69: Grade 3 – Mid-Level | I69: 3500 | J69: Yes | K69: 48.8 | L69: 68.2 | M69: =Table2[[#This Row],[Post-Training Score]]-Table2[[#This Row],[Pre-Training Score]] -> 19.4 | N69: =(Table2[[#This Row],[Score Improvement]]/Table2[[#This Row],[Pre-Training Score]]) -> 0.39754098
A70: TRN-3002 | B70: Leadership Development | C70: Leadership | D70: 45567 | E70: 3 | F70: EMP-15390 | G70: Finance | H70: Grade 5 – Lead | I70: 3500 | J70: Yes | K70: 48.4 | L70: 82.8 | M70: =Table2[[#This Row],[Post-Training Score]]-Table2[[#This Row],[Pre-Training Score]] -> 34.4 | N70: =(Table2[[#This Row],[Score Improvement]]/Table2[[#This Row],[Pre-Training Score]]) -> 0.7107438
A71: TRN-3002 | B71: Leadership Development | C71: Leadership | D71: 45567 | E71: 3 | F71: EMP-15325 | G71: Legal | H71: Grade 5 – Lead | I71: 3500 | J71: Yes | K71: 51.7 | L71: 78.8 | M71: =Table2[[#This Row],[Post-Training Score]]-Table2[[#This Row],[Pre-Training Score]] -> 27.1 | N71: =(Table2[[#This Row],[Score Improvement]]/Table2[[#This Row],[Pre-Training Score]]) -> 0.52417795
A72: TRN-3002 | B72: Leadership Development | C72: Leadership | D72: 45567 | E72: 3 | F72: EMP-11718 | G72: Human Resources | H72: Grade 2 – Junior | I72: 3500 | J72: No | M72: =Table2[[#This Row],[Post-Training Score]]-Table2[[#This Row],[Pre-Training Score]] -> 0 | N72: =(Table2[[#This Row],[Score Improvement]]/Table2[[#This Row],[Pre-Training Score]]) -> #DIV/0!
A73: TRN-3002 | B73: Leadership Development | C73: Leadership | D73: 45567 | E73: 3 | F73: EMP-13811 | G73: Risk & Compliance | H73: Grade 4 – Senior | I73: 3500 | J73: Yes | K73: 62.1 | L73: 87.6 | M73: =Table2[[#This Row],[Post-Training Score]]-Table2[[#This Row],[Pre-Training Score]] -> 25.5 | N73: =(Table2[[#This Row],[Score Improvement]]/Table2[[#This Row],[Pre-Training Score]]) -> 0.41062802
A74: TRN-3002 | B74: Leadership Development | C74: Leadership | D74: 45567 | E74: 3 | F74: EMP-14621 | G74: Human Resources | H74: Grade 3 – Mid-Level | I74: 3500 | J74: Yes | K74: 66.7 | L74: 91.1 | M74: =Table2[[#This Row],[Post-Training Score]]-Table2[[#This Row],[Pre-Training Score]] -> 24.4 | N74: =(Table2[[#This Row],[Score Improvement]]/Table2[[#This Row],[Pre-Training Score]]) -> 0.36581709
A75: TRN-3002 | B75: Leadership Development | C75: Leadership | D75: 45567 | E75: 3 | F75: EMP-10318 | G75: Procurement | H75: Grade 2 – Junior | I75: 3500 | J75: Yes | K75: 65.6 | L75: 77.1 | M75: =Table2[[#This Row],[Post-Training Score]]-Table2[[#This Row],[Pre-Training Score]] -> 11.5 | N75: =(Table2[[#This Row],[Score Improvement]]/Table2[[#This Row],[Pre-Training Score]]) -> 0.17530488
A76: TRN-3002 | B76: Leadership Development | C76: Leadership | D76: 45567 | E76: 3 | F76: EMP-12915 | G76: Sales | H76: Grade 6 – Manager | I76: 3500 | J76: Yes | K76: 48.1 | L76: 66.4 | M76: =Table2[[#This Row],[Post-Training Score]]-Table2[[#This Row],[Pre-Training Score]] -> 18.3 | N76: =(Table2[[#This Row],[Score Improvement]]/Table2[[#This Row],[Pre-Training Score]]) -> 0.38045738
A77: TRN-3002 | B77: Leadership Development | C77: Leadership | D77: 45567 | E77: 3 | F77: EMP-12736 | G77: Human Resources | H77: Grade 3 – Mid-Level | I77: 3500 | J77: Yes | K77: 42.8 | L77: 77.7 | M77: =Table2[[#This Row],[Post-Training Score]]-Table2[[#This Row],[Pre-Training Score]] -> 34.9 | N77: =(Table2[[#This Row],[Score Improvement]]/Table2[[#This Row],[Pre-Training Score]]) -> 0.81542056
A78: TRN-3002 | B78: Leadership Development | C78: Leadership | D78: 45567 | E78: 3 | F78: EMP-13465 | G78: Legal | H78: Grade 3 – Mid-Level | I78: 3500 | J78: Yes | K78: 57.6 | L78: 70.3 | M78: =Table2[[#This Row],[Post-Training Score]]-Table2[[#This Row],[Pre-Training Score]] -> 12.7 | N78: =(Table2[[#This Row],[Score Improvement]]/Table2[[#This Row],[Pre-Training Score]]) -> 0.22048611
A79: TRN-3002 | B79: Leadership Development | C79: Leadership | D79: 45567 | E79: 3 | F79: EMP-13572 | G79: Sales | H79: Grade 1 – Entry | I79: 3500 | J79: Yes | K79: 72.7 | L79: 91 | M79: =Table2[[#This Row],[Post-Training Score]]-Table2[[#This Row],[Pre-Training Score]] -> 18.3 | N79: =(Table2[[#This Row],[Score Improvement]]/Table2[[#This Row],[Pre-Training Score]]) -> 0.25171939
A80: TRN-3002 | B80: Leadership Development | C80: Leadership | D80: 45567 | E80: 3 | F80: EMP-12617 | G80: Executive Management | H80: Grade 5 – Lead | I80: 3500 | J80: Yes | K80: 74.4 | L80: 81.3 | M80: =Table2[[#This Row],[Post-Training Score]]-Table2[[#This Row],[Pre-Training Score]] -> 6.9 | N80: =(Table2[[#This Row],[Score Improvement]]/Table2[[#This Row],[Pre-Training Score]]) -> 0.092741935
A81: TRN-3002 | B81: Leadership Development | C81: Leadership | D81: 45567 | E81: 3 | F81: EMP-11683 | G81: Operations | H81: Grade 4 – Senior | I81: 3500 | J81: Yes | K81: 68.1 | L81: 82.4 | M81: =Table2[[#This Row],[Post-Training Score]]-Table2[[#This Row],[Pre-Training Score]] -> 14.3 | N81: =(Table2[[#This Row],[Score Improvement]]/Table2[[#This Row],[Pre-Training Score]]) -> 0.20998532
A82: TRN-3002 | B82: Leadership Development | C82: Leadership | D82: 45567 | E82: 3 | F82: EMP-12536 | G82: Human Resources | H82: Grade 6 – Manager | I82: 3500 | J82: Yes | K82: 44.6 | L82: 54.7 | M82: =Table2[[#This Row],[Post-Training Score]]-Table2[[#This Row],[Pre-Training Score]] -> 10.1 | N82: =(Table2[[#This Row],[Score Improvement]]/Table2[[#This Row],[Pre-Training Score]]) -> 0.2264574
A83: TRN-3002 | B83: Leadership Development | C83: Leadership | D83: 45567 | E83: 3 | F83: EMP-13767 | G83: Information Technology | H83: Grade 4 – Senior | I83: 3500 | J83: Yes | K83: 73.1 | L83: 95.5 | M83: =Table2[[#This Row],[Post-Training Score]]-Table2[[#This Row],[Pre-Training Score]] -> 22.4 | N83: =(Table2[[#This Row],[Score Improvement]]/Table2[[#This Row],[Pre-Training Score]]) -> 0.30642955
A84: TRN-3002 | B84: Leadership Development | C84: Leadership | D84: 45567 | E84: 3 | F84: EMP-15263 | G84: Executive Management | H84: Grade 8 – Executive | I84: 3500 | J84: Yes | K84: 40.2 | L84: 58.6 | M84: =Table2[[#This Row],[Post-Training Score]]-Table2[[#This Row],[Pre-Training Score]] -> 18.4 | N84: =(Table2[[#This Row],[Score Improvement]]/Table2[[#This Row],[Pre-Training Score]]) -> 0.45771144
... A91: TRN-3002 | B91: Leadership Development | C91: Leadership | D91: 45567 | E91: 3 | F91: EMP-12414 | G91: Executive Management | H91: Grade 5 – Lead | I91: 3500 | J91: Yes | K91: 43.6 | L91: 63.6 | M91: =Table2[[#This Row],[Post-Training Score]]-Table2[[#This Row],[Pre-Training Score]] -> 20 | N91: =(Table2[[#This Row],[Score Improvement]]/Table2[[#This Row],[Pre-Training Score]]) -> 0.4587156
A92: TRN-3002 | B92: Leadership Development | C92: Leadership | D92: 45567 | E92: 3 | F92: EMP-10469 | G92: Finance | H92: Grade 4 – Senior | I92: 3500 | J92: No | M92: =Table2[[#This Row],[Post-Training Score]]-Table2[[#This Row],[Pre-Training Score]] -> 0 | N92: =(Table2[[#This Row],[Score Improvement]]/Table2[[#This Row],[Pre-Training Score]]) -> #DIV/0!
A93: TRN-3002 | B93: Leadership Development | C93: Leadership | D93: 45567 | E93: 3 | F93: EMP-12904 | G93: Risk & Compliance | H93: Grade 1 – Entry | I93: 3500 | J93: Yes | K93: 63.5 | L93: 72.1 | M93: =Table2[[#This Row],[Post-Training Score]]-Table2[[#This Row],[Pre-Training Score]] -> 8.6 | N93: =(Table2[[#This Row],[Score Improvement]]/Table2[[#This Row],[Pre-Training Score]]) -> 0.13543307
A94: TRN-3002 | B94: Leadership Development | C94: Leadership | D94: 45567 | E94: 3 | F94: EMP-14666 | G94: Marketing | H94: Grade 2 – Junior | I94: 3500 | J94: Yes | K94: 54.4 | L94: 85.8 | M94: =Table2[[#This Row],[Post-Training Score]]-Table2[[#This Row],[Pre-Training Score]] -> 31.4 | N94: =(Table2[[#This Row],[Score Improvement]]/Table2[[#This Row],[Pre-Training Score]]) -> 0.57720588
A95: TRN-3002 | B95: Leadership Development | C95: Leadership | D95: 45567 | E95: 3 | F95: EMP-12717 | G95: Risk & Compliance | H95: Grade 3 – Mid-Level | I95: 3500 | J95: Yes | K95: 46.2 | L95: 59.5 | M95: =Table2[[#This Row],[Post-Training Score]]-Table2[[#This Row],[Pre-Training Score]] -> 13.3 | N95: =(Table2[[#This Row],[Score Improvement]]/Table2[[#This Row],[Pre-Training Score]]) -> 0.28787879
A96: TRN-3002 | B96: Leadership Development | C96: Leadership | D96: 45567 | E96: 3 | F96: EMP-15252 | G96: Legal | H96: Grade 3 – Mid-Level | I96: 3500 | J96: Yes | K96: 72.3 | L96: 82.7 | M96: =Table2[[#This Row],[Post-Training Score]]-Table2[[#This Row],[Pre-Training Score]] -> 10.4 | N96: =(Table2[[#This Row],[Score Improvement]]/Table2[[#This Row],[Pre-Training Score]]) -> 0.14384509
A97: TRN-3002 | B97: Leadership Development | C97: Leadership | D97: 45567 | E97: 3 | F97: EMP-15253 | G97: Procurement | H97: Grade 5 – Lead | I97: 3500 | J97: Yes | K97: 71.8 | L97: 98.8 | M97: =Table2[[#This Row],[Post-Training Score]]-Table2[[#This Row],[Pre-Training Score]] -> 27 | N97: =(Table2[[#This Row],[Score Improvement]]/Table2[[#This Row],[Pre-Training Score]]) -> 0.37604457
A98: TRN-3002 | B98: Leadership Development | C98: Leadership | D98: 45567 | E98: 3 | F98: EMP-12403 | G98: Executive Management | H98: Grade 7 – Director | I98: 3500 | J98: Yes | K98: 57.3 | L98: 84.4 | M98: =Table2[[#This Row],[Post-Training Score]]-Table2[[#This Row],[Pre-Training Score]] -> 27.1 | N98: =(Table2[[#This Row],[Score Improvement]]/Table2[[#This Row],[Pre-Training Score]]) -> 0.47294939
A99: TRN-3002 | B99: Leadership Development | C99: Leadership | D99: 45567 | E99: 3 | F99: EMP-10069 | G99: Information Technology | H99: Grade 1 – Entry | I99: 3500 | J99: Yes | K99: 48.1 | L99: 67.5 | M99: =Table2[[#This Row],[Post-Training Score]]-Table2[[#This Row],[Pre-Training Score]] -> 19.4 | N99: =(Table2[[#This Row],[Score Improvement]]/Table2[[#This Row],[Pre-Training Score]]) -> 0.4033264
A100: TRN-3002 | B100: Leadership Development | C100: Leadership | D100: 45567 | E100: 3 | F100: EMP-11252 | G100: Customer Service | H100: Grade 2 – Junior | I100: 3500 | J100: Yes | K100: 53.7 | L100: 85.7 | M100: =Table2[[#This Row],[Post-Training Score]]-Table2[[#This Row],[Pre-Training Score]] -> 32 | N100: =(Table2[[#This Row],[Score Improvement]]/Table2[[#This Row],[Pre-Training Score]]) -> 0.59590317
A101: TRN-3002 | B101: Leadership Development | C101: Leadership | D101: 45567 | E101: 3 | F101: EMP-15351 | G101: Procurement | H101: Grade 4 – Senior | I101: 3500 | J101: Yes | K101: 67.3 | L101: 78.9 | M101: =Table2[[#This Row],[Post-Training Score]]-Table2[[#This Row],[Pre-Training Score]] -> 11.6 | N101: =(Table2[[#This Row],[Score Improvement]]/Table2[[#This Row],[Pre-Training Score]]) -> 0.17236256
A102: TRN-3002 | B102: Leadership Development | C102: Leadership | D102: 45567 | E102: 3 | F102: EMP-14359 | G102: Operations | H102: Grade 2 – Junior | I102: 3500 | J102: Yes | K102: 43.4 | L102: 67.6 | M102: =Table2[[#This Row],[Post-Training Score]]-Table2[[#This Row],[Pre-Training Score]] -> 24.2 | N102: =(Table2[[#This Row],[Score Improvement]]/Table2[[#This Row],[Pre-Training Score]]) -> 0.55760369
A103: TRN-3002 | B103: Leadership Development | C103: Leadership | D103: 45567 | E103: 3 | F103: EMP-10528 | G103: Procurement | H103: Grade 4 – Senior | I103: 3500 | J103: Yes | K103: 49.7 | L103: 71.6 | M103: =Table2[[#This Row],[Post-Training Score]]-Table2[[#This Row],[Pre-Training Score]] -> 21.9 | N103: =(Table2[[#This Row],[Score Improvement]]/Table2[[#This Row],[Pre-Training Score]]) -> 0.44064386
A104: TRN-3002 | B104: Leadership Development | C104: Leadership | D104: 45567 | E104: 3 | F104: EMP-10295 | G104: Human Resources | H104: Grade 4 – Senior | I104: 3500 | J104: Yes | K104: 70.8 | L104: 90.3 | M104: =Table2[[#This Row],[Post-Training Score]]-Table2[[#This Row],[Pre-Training Score]] -> 19.5 | N104: =(Table2[[#This Row],[Score Improvement]]/Table2[[#This Row],[Pre-Training Score]]) -> 0.27542373
... A146: TRN-3004 | B146: Excel & Data Analytics | C146: Technical | D146: 45595 | E146: 1 | F146: EMP-13251 | G146: Information Technology | H146: Grade 3 – Mid-Level | I146: 1200 | J146: Yes | K146: 62.5 | L146: 86.6 | M146: =Table2[[#This Row],[Post-Training Score]]-Table2[[#This Row],[Pre-Training Score]] -> 24.1 | N146: =(Table2[[#This Row],[Score Improvement]]/Table2[[#This Row],[Pre-Training Score]]) -> 0.3856
A147: TRN-3004 | B147: Excel & Data Analytics | C147: Technical | D147: 45595 | E147: 1 | F147: EMP-14890 | G147: Human Resources | H147: Grade 4 – Senior | I147: 1200 | J147: No | M147: =Table2[[#This Row],[Post-Training Score]]-Table2[[#This Row],[Pre-Training Score]] -> 0 | N147: =(Table2[[#This Row],[Score Improvement]]/Table2[[#This Row],[Pre-Training Score]]) -> #DIV/0!
A148: TRN-3004 | B148: Excel & Data Analytics | C148: Technical | D148: 45595 | E148: 1 | F148: EMP-15207 | G148: Customer Service | H148: Grade 2 – Junior | I148: 1200 | J148: Yes | K148: 55.4 | L148: 62.4 | M148: =Table2[[#This Row],[Post-Training Score]]-Table2[[#This Row],[Pre-Training Score]] -> 7 | N148: =(Table2[[#This Row],[Score Improvement]]/Table2[[#This Row],[Pre-Training Score]]) -> 0.12635379
A149: TRN-3004 | B149: Excel & Data Analytics | C149: Technical | D149: 45595 | E149: 1 | F149: EMP-14385 | G149: Procurement | H149: Grade 4 – Senior | I149: 1200 | J149: No | M149: =Table2[[#This Row],[Post-Training Score]]-Table2[[#This Row],[Pre-Training Score]] -> 0 | N149: =(Table2[[#This Row],[Score Improvement]]/Table2[[#This Row],[Pre-Training Score]]) -> #DIV/0!
A150: TRN-3004 | B150: Excel & Data Analytics | C150: Technical | D150: 45595 | E150: 1 | F150: EMP-12653 | G150: Finance | H150: Grade 4 – Senior | I150: 1200 | J150: Yes | K150: 74 | L150: 100 | M150: =Table2[[#This Row],[Post-Training Score]]-Table2[[#This Row],[Pre-Training Score]] -> 26 | N150: =(Table2[[#This Row],[Score Improvement]]/Table2[[#This Row],[Pre-Training Score]]) -> 0.35135135
A151: TRN-3004 | B151: Excel & Data Analytics | C151: Technical | D151: 45595 | E151: 1 | F151: EMP-12849 | G151: Finance | H151: Grade 5 – Lead | I151: 1200 | J151: Yes | K151: 74 | L151: 86 | M151: =Table2[[#This Row],[Post-Training Score]]-Table2[[#This Row],[Pre-Training Score]] -> 12 | N151: =(Table2[[#This Row],[Score Improvement]]/Table2[[#This Row],[Pre-Training Score]]) -> 0.16216216
A152: TRN-3004 | B152: Excel & Data Analytics | C152: Technical | D152: 45595 | E152: 1 | F152: EMP-15455 | G152: Finance | H152: Grade 7 – Director | I152: 1200 | J152: No | M152: =Table2[[#This Row],[Post-Training Score]]-Table2[[#This Row],[Pre-Training Score]] -> 0 | N152: =(Table2[[#This Row],[Score Improvement]]/Table2[[#This Row],[Pre-Training Score]]) -> #DIV/0!
A153: TRN-3004 | B153: Excel & Data Analytics | C153: Technical | D153: 45595 | E153: 1 | F153: EMP-11677 | G153: Executive Management | H153: Grade 6 – Manager | I153: 1200 | J153: Yes | K153: 67.1 | L153: 60 | M153: =Table2[[#This Row],[Post-Training Score]]-Table2[[#This Row],[Pre-Training Score]] -> -7.1 | N153: =(Table2[[#This Row],[Score Improvement]]/Table2[[#This Row],[Pre-Training Score]]) -> -0.10581222
A154: TRN-3004 | B154: Excel & Data Analytics | C154: Technical | D154: 45595 | E154: 1 | F154: EMP-14439 | G154: Operations | H154: Grade 3 – Mid-Level | I154: 1200 | J154: Yes | K154: 47.2 | L154: 55 | M154: =Table2[[#This Row],[Post-Training Score]]-Table2[[#This Row],[Pre-Training Score]] -> 7.8 | N154: =(Table2[[#This Row],[Score Improvement]]/Table2[[#This Row],[Pre-Training Score]]) -> 0.16525424
A155: TRN-3004 | B155: Excel & Data Analytics | C155: Technical | D155: 45595 | E155: 1 | F155: EMP-10836 | G155: Marketing | H155: Grade 4 – Senior | I155: 1200 | J155: Yes | K155: 62.6 | L155: 60 | M155: =Table2[[#This Row],[Post-Training Score]]-Table2[[#This Row],[Pre-Training Score]] -> -2.6 | N155: =(Table2[[#This Row],[Score Improvement]]/Table2[[#This Row],[Pre-Training Score]]) -> -0.041533546
A156: TRN-3004 | B156: Excel & Data Analytics | C156: Technical | D156: 45595 | E156: 1 | F156: EMP-11727 | G156: Customer Service | H156: Grade 2 – Junior | I156: 1200 | J156: Yes | K156: 70.6 | L156: 92.3 | M156: =Table2[[#This Row],[Post-Training Score]]-Table2[[#This Row],[Pre-Training Score]] -> 21.7 | N156: =(Table2[[#This Row],[Score Improvement]]/Table2[[#This Row],[Pre-Training Score]]) -> 0.30736544
A157: TRN-3004 | B157: Excel & Data Analytics | C157: Technical | D157: 45595 | E157: 1 | F157: EMP-10135 | G157: Procurement | H157: Grade 3 – Mid-Level | I157: 1200 | J157: Yes | K157: 64.4 | L157: 60 | M157: =Table2[[#This Row],[Post-Training Score]]-Table2[[#This Row],[Pre-Training Score]] -> -4.4 | N157: =(Table2[[#This Row],[Score Improvement]]/Table2[[#This Row],[Pre-Training Score]]) -> -0.068322981
A158: TRN-3004 | B158: Excel & Data Analytics | C158: Technical | D158: 45595 | E158: 1 | F158: EMP-13225 | G158: Executive Management | H158: Grade 8 – Executive | I158: 1200 | J158: Yes | K158: 42.2 | L158: 43.4 | M158: =Table2[[#This Row],[Post-Training Score]]-Table2[[#This Row],[Pre-Training Score]] -> 1.2 | N158: =(Table2[[#This Row],[Score Improvement]]/Table2[[#This Row],[Pre-Training Score]]) -> 0.028436019
A159: TRN-3004 | B159: Excel & Data Analytics | C159: Technical | D159: 45595 | E159: 1 | F159: EMP-11514 | G159: Operations | H159: Grade 2 – Junior | I159: 1200 | J159: Yes | K159: 59.1 | L159: 43.4 | M159: =Table2[[#This Row],[Post-Training Score]]-Table2[[#This Row],[Pre-Training Score]] -> -15.7 | N159: =(Table2[[#This Row],[Score Improvement]]/Table2[[#This Row],[Pre-Training Score]]) -> -0.26565144
A160: TRN-3004 | B160: Excel & Data Analytics | C160: Technical | D160: 45595 | E160: 1 | F160: EMP-15246 | G160: Sales | H160: Grade 3 – Mid-Level | I160: 1200 | J160: Yes | K160: 51.5 | L160: 43.4 | M160: =Table2[[#This Row],[Post-Training Score]]-Table2[[#This Row],[Pre-Training Score]] -> -8.1 | N160: =(Table2[[#This Row],[Score Improvement]]/Table2[[#This Row],[Pre-Training Score]]) -> -0.15728155
A161: TRN-3004 | B161: Excel & Data Analytics | C161: Technical | D161: 45595 | E161: 1 | F161: EMP-14581 | G161: Sales | H161: Grade 4 – Senior | I161: 1200 | J161: Yes | K161: 52.6 | L161: 43.4 | M161: =Table2[[#This Row],[Post-Training Score]]-Table2[[#This Row],[Pre-Training Score]] -> -9.2 | N161: =(Table2[[#This Row],[Score Improvement]]/Table2[[#This Row],[Pre-Training Score]]) -> -0.17490494
A162: TRN-3004 | B162: Excel & Data Analytics | C162: Technical | D162: 45595 | E162: 1 | F162: EMP-10284 | G162: Sales | H162: Grade 3 – Mid-Level | I162: 1200 | J162: Yes | K162: 62.1 | L162: 43.4 | M162: =Table2[[#This Row],[Post-Training Score]]-Table2[[#This Row],[Pre-Training Score]] -> -18.7 | N162: =(Table2[[#This Row],[Score Improvement]]/Table2[[#This Row],[Pre-Training Score]]) -> -0.30112721
A163: TRN-3004 | B163: Excel & Data Analytics | C163: Technical | D163: 45595 | E163: 1 | F163: EMP-10374 | G163: Finance | H163: Grade 5 – Lead | I163: 1200 | J163: Yes | K163: 47.2 | L163: 43.4 | M163: =Table2[[#This Row],[Post-Training Score]]-Table2[[#This Row],[Pre-Training Score]] -> -3.8 | N163: =(Table2[[#This Row],[Score Improvement]]/Table2[[#This Row],[Pre-Training Score]]) -> -0.080508475
A164: TRN-3004 | B164: Excel & Data Analytics | C164: Technical | D164: 45595 | E164: 1 | F164: EMP-11255 | G164: Risk & Compliance | H164: Grade 5 – Lead | I164: 1200 | J164: Yes | K164: 62.7 | L164: 43.4 | M164: =Table2[[#This Row],[Post-Training Score]]-Table2[[#This Row],[Pre-Training Score]] -> -19.3 | N164: =(Table2[[#This Row],[Score Improvement]]/Table2[[#This Row],[Pre-Training Score]]) -> -0.30781499
A165: TRN-3004 | B165: Excel & Data Analytics | C165: Technical | D165: 45595 | E165: 1 | F165: EMP-10501 | G165: Customer Service | H165: Grade 2 – Junior | I165: 1200 | J165: No | M165: =Table2[[#This Row],[Post-Training Score]]-Table2[[#This Row],[Pre-Training Score]] -> 0 | N165: =(Table2[[#This Row],[Score Improvement]]/Table2[[#This Row],[Pre-Training Score]]) -> #DIV/0!
A166: TRN-3004 | B166: Excel & Data Analytics | C166: Technical | D166: 45595 | E166: 1 | F166: EMP-13868 | G166: Finance | H166: Grade 3 – Mid-Level | I166: 1200 | J166: Yes | K166: 70.7 | L166: 98.5 | M166: =Table2[[#This Row],[Post-Training Score]]-Table2[[#This Row],[Pre-Training Score]] -> 27.8 | N166: =(Table2[[#This Row],[Score Improvement]]/Table2[[#This Row],[Pre-Training Score]]) -> 0.39321075
A167: TRN-3004 | B167: Excel & Data Analytics | C167: Technical | D167: 45595 | E167: 1 | F167: EMP-11619 | G167: Sales | H167: Grade 5 – Lead | I167: 1200 | J167: Yes | K167: 41.7 | L167: 47.3 | M167: =Table2[[#This Row],[Post-Training Score]]-Table2[[#This Row],[Pre-Training Score]] -> 5.6 | N167: =(Table2[[#This Row],[Score Improvement]]/Table2[[#This Row],[Pre-Training Score]]) -> 0.13429257
A168: TRN-3004 | B168: Excel & Data Analytics | C168: Technical | D168: 45595 | E168: 1 | F168: EMP-12949 | G168: Operations | H168: Grade 4 – Senior | I168: 1200 | J168: Yes | K168: 64.7 | L168: 71.8 | M168: =Table2[[#This Row],[Post-Training Score]]-Table2[[#This Row],[Pre-Training Score]] -> 7.1 | N168: =(Table2[[#This Row],[Score Improvement]]/Table2[[#This Row],[Pre-Training Score]]) -> 0.10973725
A169: TRN-3004 | B169: Excel & Data Analytics | C169: Technical | D169: 45595 | E169: 1 | F169: EMP-14372 | G169: Marketing | H169: Grade 4 – Senior | I169: 1200 | J169: Yes | K169: 50.2 | L169: 68.2 | M169: =Table2[[#This Row],[Post-Training Score]]-Table2[[#This Row],[Pre-Training Score]] -> 18 | N169: =(Table2[[#This Row],[Score Improvement]]/Table2[[#This Row],[Pre-Training Score]]) -> 0.35856574
A170: TRN-3004 | B170: Excel & Data Analytics | C170: Technical | D170: 45595 | E170: 1 | F170: EMP-13817 | G170: Information Technology | H170: Grade 3 – Mid-Level | I170: 1200 | J170: Yes | K170: 55.2 | L170: 70.4 | M170: =Table2[[#This Row],[Post-Training Score]]-Table2[[#This Row],[Pre-Training Score]] -> 15.2 | N170: =(Table2[[#This Row],[Score Improvement]]/Table2[[#This Row],[Pre-Training Score]]) -> 0.27536232
A171: TRN-3004 | B171: Excel & Data Analytics | C171: Technical | D171: 45595 | E171: 1 | F171: EMP-11558 | G171: Marketing | H171: Grade 2 – Junior | I171: 1200 | J171: Yes | K171: 68.3 | L171: 79.1 | M171: =Table2[[#This Row],[Post-Training Score]]-Table2[[#This Row],[Pre-Training Score]] -> 10.8 | N171: =(Table2[[#This Row],[Score Improvement]]/Table2[[#This Row],[Pre-Training Score]]) -> 0.15812592
...

Sheet RECRUITMENT TRACKER
A1: Requisition ID | B1: Department | C1: Branch | D1: Job Grade | E1: Date Posted | F1: Date Closed | G1: Time to Fill (Days) | H1: Applications Received | I1: Shortlisted | J1: Interviewed | K1: Hired | L1: Hire Source | M1: Hired Employee ID | N1: Recruitment Cost ($) | O1: Status
A2: REQ-2025-1001 | B2: Sales | C2: Head Office | D2: Grade 2 – Junior | E2: 45952 | F2: 46033 | G2: 81 | H2: 91 | I2: 22 | J2: 14 | K2: 1 | L2: Job Portal | M2: EMP-10002 | N2: 548 | O2: Closed – Filled
A3: REQ-2025-1002 | B3: Information Technology | C3: Head Office | D3: Grade 5 – Lead | E3: 45875 | F3: 45960 | G3: 85 | H3: 82 | I3: 12 | J3: 7 | K3: 1 | L3: LinkedIn | M3: EMP-10003 | N3: 710 | O3: Closed – Filled
A4: REQ-2024-1003 | B4: Information Technology | C4: East Region | D4: Grade 5 – Lead | E4: 45418 | F4: 45465 | G4: 47 | H4: 36 | I4: 18 | J4: 14 | K4: 1 | L4: Job Portal | M4: EMP-10005 | N4: 456 | O4: Closed – Filled
A5: REQ-2024-1004 | B5: Customer Service | C5: South Region | D5: Grade 3 – Mid-Level | E5: 45604 | F5: 45662 | G5: 58 | H5: 21 | I5: 5 | J5: 5 | K5: 1 | L5: Employee Referral | M5: EMP-10013 | N5: 58 | O5: Closed – Filled
A6: REQ-2025-1005 | B6: Information Technology | C6: North Region | D6: Grade 4 – Senior | E6: 45390 | F6: 45439 | G6: 49 | H6: 76 | I6: 29 | J6: 10 | K6: 1 | L6: Job Portal | M6: EMP-10019 | N6: 405 | O6: Closed – Filled
A7: REQ-2025-1006 | B7: Human Resources | C7: South Region | D7: Grade 4 – Senior | E7: 46061 | F7: 46087 | G7: 26 | H7: 63 | I7: 22 | J7: 7 | K7: 1 | L7: Job Portal | M7: EMP-10020 | N7: 348 | O7: Closed – Filled
A8: REQ-2025-1007 | B8: Risk & Compliance | C8: Head Office | D8: Grade 3 – Mid-Level | E8: 45337 | F8: 45377 | G8: 40 | H8: 101 | I8: 6 | J8: 6 | K8: 1 | L8: Employee Referral | M8: EMP-10024 | N8: 292 | O8: Closed – Filled
A9: REQ-2025-1008 | B9: Customer Service | C9: Central Hub | D9: Grade 1 – Entry | E9: 45836 | F9: 45866 | G9: 30 | H9: 114 | I9: 10 | J9: 4 | K9: 1 | L9: Recruitment Agency | M9: EMP-10026 | N9: 3045 | O9: Closed – Filled
A10: REQ-2025-1009 | B10: Legal | C10: Head Office | D10: Grade 6 – Manager | E10: 45620 | F10: 45645 | G10: 25 | H10: 17 | I10: 14 | J10: 11 | K10: 1 | L10: Recruitment Agency | M10: EMP-10028 | N10: 2967 | O10: Closed – Filled
A11: REQ-2024-1010 | B11: Executive Management | C11: Head Office | D11: Grade 7 – Director | E11: 45763 | F11: 45818 | G11: 55 | H11: 29 | I11: 8 | J11: 8 | K11: 1 | L11: Employee Referral | M11: EMP-10030 | N11: 145 | O11: Closed – Filled
A12: REQ-2024-1011 | B12: Customer Service | C12: West Region | D12: Grade 3 – Mid-Level | E12: 45881 | F12: 45931 | G12: 50 | H12: 66 | I12: 14 | J12: 10 | K12: 1 | L12: LinkedIn | M12: EMP-10033 | N12: 397 | O12: Closed – Filled
A13: REQ-2024-1012 | B13: Information Technology | C13: West Region | D13: Grade 3 – Mid-Level | E13: 45233 | F13: 45297 | G13: 64 | H13: 93 | I13: 26 | J13: 14 | K13: 1 | L13: Recruitment Agency | M13: EMP-10038 | N13: 1130 | O13: Closed – Filled
... A1486: REQ-2025-2485 | B1486: Finance | C1486: Central Hub | D1486: Grade 6 – Manager | E1486: 45933 | F1486: 46022 | G1486: 89 | H1486: 38 | I1486: 27 | J1486: 9 | K1486: 1 | L1486: Recruitment Agency | M1486: EMP-15494 | N1486: 2239 | O1486: Closed – Filled
A1487: REQ-2026-2486 | B1487: Finance | C1487: East Region | D1487: Grade 3 – Mid-Level | E1487: 46118 | G1487: 42 | H1487: 32 | I1487: 11 | J1487: 8 | K1487: 0 | L1487: Job Portal | M1487: N/A | N1487: 176 | O1487: In Progress – Interviewing
A1488: REQ-2026-2487 | B1488: Operations | C1488: South Region | D1488: Grade 3 – Mid-Level | E1488: 46088 | G1488: 72 | H1488: 11 | I1488: 7 | J1488: 7 | K1488: 0 | L1488: University Career Fair | M1488: N/A | N1488: 417 | O1488: Open
A1489: REQ-2026-2488 | B1489: Sales | C1489: North Region | D1489: Grade 2 – Junior | E1489: 46061 | G1489: 99 | H1489: 57 | I1489: 8 | J1489: 1 | K1489: 0 | L1489: Employee Referral | M1489: N/A | N1489: 514 | O1489: In Progress – Interviewing
A1490: REQ-2026-2489 | B1490: Customer Service | C1490: North Region | D1490: Grade 3 – Mid-Level | E1490: 46048 | G1490: 112 | H1490: 18 | I1490: 5 | J1490: 1 | K1490: 0 | L1490: University Career Fair | M1490: N/A | N1490: 101 | O1490: Offer Extended
A1491: REQ-2026-2490 | B1491: Customer Service | C1491: South Region | D1491: Grade 2 – Junior | E1491: 46042 | G1491: 118 | H1491: 7 | I1491: 7 | J1491: 3 | K1491: 0 | L1491: Recruitment Agency | M1491: N/A | N1491: 59 | O1491: In Progress – Interviewing
A1492: REQ-2026-2491 | B1492: Sales | C1492: Central Hub | D1492: Grade 2 – Junior | E1492: 46029 | G1492: 131 | H1492: 26 | I1492: 19 | J1492: 6 | K1492: 0 | L1492: Recruitment Agency | M1492: N/A | N1492: 423 | O1492: In Progress – Interviewing
A1493: REQ-2026-2492 | B1493: Human Resources | C1493: South Region | D1493: Grade 4 – Senior | E1493: 46083 | G1493: 77 | H1493: 52 | I1493: 10 | J1493: 4 | K1493: 0 | L1493: University Career Fair | M1493: N/A | N1493: 307 | O1493: In Progress – Interviewing
A1494: REQ-2026-2493 | B1494: Information Technology | C1494: Head Office | D1494: Grade 5 – Lead | E1494: 46108 | G1494: 52 | H1494: 45 | I1494: 11 | J1494: 3 | K1494: 0 | L1494: Recruitment Agency | M1494: N/A | N1494: 336 | O1494: In Progress – Interviewing
A1495: REQ-2026-2494 | B1495: Legal | C1495: Head Office | D1495: Grade 4 – Senior | E1495: 46100 | G1495: 60 | H1495: 10 | I1495: 4 | J1495: 2 | K1495: 0 | L1495: LinkedIn | M1495: N/A | N1495: 763 | O1495: Open
A1496: REQ-2026-2495 | B1496: Procurement | C1496: North Region | D1496: Grade 5 – Lead | E1496: 46141 | G1496: 19 | H1496: 42 | I1496: 11 | J1496: 5 | K1496: 0 | L1496: LinkedIn | M1496: N/A | N1496: 292 | O1496: Offer Extended
A1497: REQ-2026-2496 | B1497: Operations | C1497: South Region | D1497: Grade 3 – Mid-Level | E1497: 46096 | G1497: 64 | H1497: 26 | I1497: 18 | J1497: 8 | K1497: 0 | L1497: Job Portal | M1497: N/A | N1497: 664 | O1497: Offer Extended
A1498: REQ-2026-2497 | B1498: Marketing | C1498: South Region | D1498: Grade 4 – Senior | E1498: 46023 | G1498: 137 | H1498: 59 | I1498: 10 | J1498: 6 | K1498: 0 | L1498: Job Portal | M1498: N/A | N1498: 361 | O1498: Offer Extended
... A1526: REQ-2026-2525 | B1526: Customer Service | C1526: Head Office | D1526: Grade 4 – Senior | E1526: 46094 | G1526: 66 | H1526: 20 | I1526: 8 | J1526: 1 | K1526: 0 | L1526: Job Portal | M1526: N/A | N1526: 294 | O1526: In Progress – Interviewing
